{"status":{"code":200,"name":"OK"},"data":[{"id":"608a73224d31cb16eb995d07","channelKey":"library","serviceKey":"ppss","publishKey":"608a73224d31cb16eb995d07","consumerId":"1boon","status":"published","description":"당하는 것이 당연하고, 참는 것이 당연할까? 이 드라마는 아니라고 말한다.","coverImage":"https://t1.daumcdn.net/liveboard/ppss/130cdb71bcf3429ea114e5efffb9d056.JPG","serviceTemplate":"listicle","publishTime":1619686232676,"tags":["학교폭력","드라마","모범택시","한국연예","드라마추천","한국드라마","ㅍㅍㅅㅅ","노지현"],"filteredTags":null,"bizKeywords":null,"totalShareCount":null,"shareClickCount":null,"socialIncomingCount":0,"meta":{"_tromm":"enter_general","_app":"harmony","_approvedAt":"1619686544444","_isApproved":"true"},"totalView":4,"recentView":0,"fbCommentCount":0,"useDefaultOpencomment":"true","viewCoverImage":null,"pcCoverImage":"","useLatestOrderComment":"false","cp":null,"viewCoverVideo":null,"summary":[{"title":null,"desc":"<p>드라마 &lt;펜트하우스 시즌 2 1부&gt;가 끝나고 방영되고 있는 드라마 &lt;모범택시&gt;는 &lt;펜트하우스&gt;와 다른 형태의 복수를 보여주면서 시청자들의 시선을 사로잡았다. </p> \n<p><br></p> \n<p>전작 드라마 &lt;펜트하우스&gt;가 ‘악’이라고 정의할 수 있는 인물들끼리 서로 물어뜯고 싸우는 형태의 복수가 그려졌다면, 이번 드라마 &lt;모범택시&gt;는 확실하게 나누어진 피해자와 가해자가 있으며, 각자 선과 악의 편에 선다. 이번에는 피해자를 위해 가해자에게 대신 복수하는 에피소드가 그려졌다. </p> \n<p><br></p> \n<p>지난 금요일(16일)에 방영된 드라마 &lt;모범택시 3화&gt;에서는 학교 폭력에 시달리는 피해자의 의뢰를 받는 모습이 그려졌다. 피해자는 모범택시에 전화를 걸어서 자신의 이야기를 털어놓은 이후 ‘복수를 하시겠어요?’라는 질문을 받는다. 화면에 뜬 ‘YES’ 버튼과 ‘NO’ 버튼. 피해자는 망설이다가 ‘YES’ 버튼을 누른다.</p> \n<p> </p> \n<p> </p> \n<p> </p> \n<p> </p>"},{"title":"","desc":"<p>개인적으로 이 장면이 너무나 인상적이었다. 학교 폭력은 주위에 도움을 구한다고 해서 쉽사리 해결되는 문제가 아니다. 학교에 신고해서 학교 폭력 위원회를 연다고 해도, 대다수가 흐지부지하게 결말을 맺는다. 심하면 가해자 대신 피해자가 전학을 가는 일도 발생한다. </p> \n<p><br></p> \n<p>학교에서 도움을 받을 수 없으니 당연히 피해자는 학교 폭력 신고 센터 혹은 경찰서에 의존하게 된다. 그러나 여기도 미온적인 태도가 논란된 적이 적지 않다. 결국, 학교 폭력을 해결하기 위한 절대적인 방안은 존재하지 않는다. </p> \n<p><br></p> \n<p>학교 폭력의 희생자가 되지 않기 위한 유일한 방법은 피해자가 되지 않도록 최대한 숨을 죽여 남과 같은 형태로 학교 생활을 이어나가는 것 뿐이다. 괜스레 나서다가 눈총받는 일이 없어야 하고, 일진과 마주치지 않도록 해야 하고, 가해자들이 누군가를 괴롭힐 때에는 방관자의 역할을 맡아야 한다. </p> \n<p><br></p> \n<p>그렇게 학교 폭력의 레이더망에서 빗겨가면 초등학교 6년, 중학교 3년, 고등학교 3년 동안 가혹한 학교 폭력의 울타리에서 벗어날 수 있다. 하지만 이런 방법이 옳다고 아이들에게 가르칠 수 있을까? </p> \n<p><br></p> \n<p>어른이 된 후에도 이 문제는 쉽지 않다. 사회생활에서 비일비재하게 발생하기 때문이다. 내가 어떤 직업을 가졌는지에 따라 갑질을 겪기도 하고, 대학과 군대, 직장이라는 조직 생활에서도 비슷한 폭력이 수없이 도사리고 있다. 특히 요즘 같은 시대는 더. </p> \n<p><br></p> \n<p>누군가는 이러한 상황을 체념하고 받아들이는 것이 사회생활을 해나가는 방식이라고 말한다. 원만한 사회생활을 위해서는 때때로 침묵해야 하고, 때때로 보이는 것을 보이지 않는 척하면서 살아가야 한다. 그렇게 해야만 우리는 잘살아갈 수 있다. </p> \n<p><br></p> \n<p><b>하지만 정말 그게 최선인 걸까? 당하는 것이 당연하고, 참는 것이 당연하고, 무시하는 것이 당연한 걸까?</b> 복수하면 안 되는 걸까? 이렇게 피가 마르게 만드는 가해자들에게 할 수 있는 방법은 없는 걸까? 법이 허락하지 못한다면, 그냥 이렇게 살아가야 하는 걸까?</p> \n<p> </p> \n<p> </p> \n<p> </p> \n<p> </p> \n<p> </p> \n<p> </p> \n<p> </p> \n<p> </p> \n<p> </p> \n<p> </p>"}],"title":"드라마 〈모범택시〉 죽지 말고 복수하세요","version":3,"editor":"ppss","updateTime":1619686232676,"regTime":1619686178952,"titleRaw":"드라마 〈모범택시〉 죽지 말고 복수하세요","img":"https://t1.daumcdn.net/liveboard/ppss/130cdb71bcf3429ea114e5efffb9d056.JPG","path":"ppss/608a73224d31cb16eb995d07","isHiddenComment":"false","isDisabledComment":false,"isPublic":true},{"id":"608a4d153c69bd3782375c2a","channelKey":"enter","serviceKey":"mykcatchup","publishKey":"21042901","consumerId":"1boon","status":"published","description":"급여 ★★★★★ 워라밸 ★","coverImage":"https://t1.daumcdn.net/liveboard/mykcatchup/f91d4284050343a098c79a9de3071ea9.JPG","serviceTemplate":"listicle","publishTime":1619686204102,"tags":["드라마","kbs","대박부동산","장나라","정용화","배우","신작","공포","재미","로맨스"],"filteredTags":null,"bizKeywords":null,"totalShareCount":null,"shareClickCount":null,"socialIncomingCount":88,"meta":{"_tromm":"enter_general","_app":"harmony","_approvedAt":"1619686208847","_isApproved":"true"},"totalView":163,"recentView":0,"fbCommentCount":0,"useDefaultOpencomment":"true","viewCoverImage":null,"pcCoverImage":"","useLatestOrderComment":"false","cp":null,"viewCoverVideo":null,"summary":[{"title":"","desc":"<p style=\"text-align: center; \"><br></p> \n<p style=\"text-align: center; \"><b>사무보조</b> 공고 떠서&nbsp;<span style=\"color: inherit;\"><b>면접 </b>갔더니</span></p> \n<p style=\"text-align: center; \">알고 보니 <b>퇴마 보조</b>였음</p> \n<p style=\"text-align: center; \"><i>그래... 돈을 이렇게 많이 줄리가...</i></p>"},{"title":"","desc":"<p><br></p> \n<p style=\"text-align: center; \"><b>'대박부동산'</b>은</p> \n<p style=\"text-align: center; \"><b>귀신 들린 집 정리</b>해주는 <b>부동산</b>으로,</p> \n<p style=\"text-align: center; \"><b>퇴마</b>를 하려면 귀신이 들러붙을</p> \n<p style=\"text-align: center; \">조건 맞는<b> 남자 영매</b>가 필요ㅇㅇ</p>"}],"title":"사무보조 면접 갔는데 귀신 들릴뻔했어요;;","version":12,"editor":"elTVaOipaL","updateTime":1619686204102,"regTime":1619676437705,"titleRaw":"사무보조 면접 갔는데 귀신 들릴뻔했어요;;","img":"https://t1.daumcdn.net/liveboard/mykcatchup/f91d4284050343a098c79a9de3071ea9.JPG","path":"mykcatchup/21042901","isHiddenComment":"false","isDisabledComment":false,"isPublic":true},{"id":"608a19783c69bd37823759b4","channelKey":"trending","serviceKey":"videovillage","publishKey":"608a19783c69bd37823759b4","consumerId":"1boon","status":"published","description":"하루만 니 방의 커블이 되고싶어~ 우 베이베","coverImage":"https://t1.daumcdn.net/liveboard/videovillage/af1098746ff24fb68c345663115e2e88.jpeg","serviceTemplate":"listicle","publishTime":1619686131609,"tags":[],"filteredTags":null,"bizKeywords":null,"totalShareCount":null,"shareClickCount":null,"socialIncomingCount":10,"meta":{"_tromm":"humor","_app":"harmony"},"totalView":47,"recentView":0,"fbCommentCount":0,"useDefaultOpencomment":"true","viewCoverImage":null,"pcCoverImage":"https://t1.daumcdn.net/liveboard/videovillage/af1098746ff24fb68c345663115e2e88.jpeg","useLatestOrderComment":"false","cp":null,"viewCoverVideo":null,"summary":[],"title":"하루종일 의자에 앉은 채로 살아본다면?","version":28,"editor":"EvhZ9BntXZ","updateTime":1619686474774,"regTime":1619663224065,"titleRaw":"하루종일 의자에 앉은 채로 살아본다면?","img":"https://t1.daumcdn.net/liveboard/videovillage/af1098746ff24fb68c345663115e2e88.jpeg","path":"videovillage/608a19783c69bd37823759b4","isHiddenComment":"false","isDisabledComment":true,"isPublic":true},{"id":"608a728f3c69bd3782375fb2","channelKey":"library","serviceKey":"legend","publishKey":"608a728f3c69bd3782375fb2","consumerId":"1boon","status":"published","description":"","coverImage":"https://t1.daumcdn.net/liveboard/legend/e1d39c7f48334b558bd8b764a8b7823f.jpg","serviceTemplate":"listicle","publishTime":1619686036266,"tags":["모리스라벨","모리스 라벨","Maurice Ravel","볼레로","Bolero","죽은왕녀를위한파반느"],"filteredTags":null,"bizKeywords":null,"totalShareCount":null,"shareClickCount":null,"socialIncomingCount":9,"meta":{"_tromm":"music","_app":"harmony","_approvedAt":"1619686038975","_isApproved":"true"},"totalView":18,"recentView":0,"fbCommentCount":0,"useDefaultOpencomment":"true","viewCoverImage":null,"pcCoverImage":"","useLatestOrderComment":"false","cp":null,"viewCoverVideo":null,"summary":[{"title":"프랑스 근현대 작곡가, \n<div>\n  모리스 라벨 \n</div>","desc":""},{"title":null,"desc":"<p>프랑스 벨 에포크 시대, 사람들은 살롱에 모여 교류를 나누며 문화 예술을 발전시켰다. 그런 예술가 사이에 자신만의 독특하고 아름다운 음악 세계를 펼쳐나가는 세련된 패션 감각의 한 청년이 있었다. 음악사에서 칭하는 ‘프랑스 인상주의 음악’의 대표적인 작곡가 모리스 라벨이다.&nbsp;<span style=\"color: inherit;\">그의 작품을 중심으로 모리스 라벨은 어떠한 사람인지에 대해 알아보는 시간을 가졌다.</span></p>"},{"title":"<p><b>만나 뵙게 되어 영광입니다. 선생님의 음악을 즐겨 듣는 청자로서 대화를 나눌 수 있는 기회를 주셔서 감사합니다.</b></p>","desc":"<p>반갑습니다. 제 음악이 여전히 사랑받고 있는 것에 무한한 기쁨과 감사를 드립니다. 오랜만에 저와 음악에 대한 이야기를 할 수 있는 시간이 주어진 것에 대해서도 또한 감사하게 생각하고 있습니다. 이렇게 저의 이야기를 들어주러 오셔서 기쁘네요.</p>"}],"title":"중독성 쩌는 클래식 선율, 모리스 라벨","version":2,"editor":"Gt2xKfJv0k","updateTime":1619686036266,"regTime":1619686030555,"titleRaw":"중독성 쩌는 클래식 선율,\n모리스 라벨","img":"https://t1.daumcdn.net/liveboard/legend/e1d39c7f48334b558bd8b764a8b7823f.jpg","path":"legend/608a728f3c69bd3782375fb2","isHiddenComment":"false","isDisabledComment":false,"isPublic":true},{"id":"608a3e2c18c79f2de6012df7","channelKey":"trending","serviceKey":"mango","publishKey":"Bam","consumerId":"1boon","status":"published","description":"밤가시마을 핫플이 궁금해?","coverImage":"https://t1.daumcdn.net/liveboard/mango/f534699c81124a5d82becfbe2d7fa890.png","serviceTemplate":"listicle","publishTime":1619685792154,"tags":["망고플레이트","일산","밤리단길","밤가시마을","일산맛집","밤리단길맛집","고양시"],"filteredTags":null,"bizKeywords":null,"totalShareCount":null,"shareClickCount":null,"socialIncomingCount":309,"meta":{"_tromm":"restaurant","_app":"harmony","_approvedAt":"1619685795584","_isApproved":"true"},"totalView":487,"recentView":0,"fbCommentCount":0,"useDefaultOpencomment":"true","viewCoverImage":null,"pcCoverImage":"https://t1.daumcdn.net/liveboard/mango/c30f214deb494906aee0723238209a3c.png","useLatestOrderComment":"false","cp":null,"viewCoverVideo":null,"summary":[{"title":null,"desc":"<p style=\"text-align: center;\">보넷길이라 불리는 일산 엔틱 거리가 있는 밤가시마을 일대를 요즘 밤리단길이라고 부른다고 합니다. 조용한 주택가 사이 음식점과 카페가 있어 여유로이 즐기기 좋은데요. 저희 망고플레이트가 밤리단길 맛집을 추천해드릴게요!</p> \n<p style=\"text-align: justify;\"><br></p> \n<p> </p>"},{"title":"","desc":"<p><b>카페지미스</b></p> \n<p>경기도 고양시 일산동구 일산로372번길 8</p>"},{"title":"","desc":"<p style=\"text-align: justify; \">&nbsp; 일산 양지미식당의 화려한 귀환. 미국식 스타일의 브런치 카페입니다. 이국적인 느낌의 오픈 키친에 오밀조밀 모여있는 테이블마저도 감각적으로 느껴져요.</p> \n<p style=\"text-align: justify;\"><br></p> \n<p style=\"text-align: justify; \">요즘 같이 햇살 좋은 날씨에는 야외 테라스 자리에서 즐겨보세요. 외국에 온 듯한 분위기를 느낄 수 있습니다. 그리고 육즙이 느껴지는 홈메이드 미트볼과 리코타 치즈 라자냐, 트러플 크림 뇨끼가 인기 메뉴입니다.</p>"}],"title":"일산 밤리단길 맛집 7곳","version":8,"editor":"3AY2f55BBX","updateTime":1619685792154,"regTime":1619672620407,"titleRaw":"일산 밤리단길 맛집 7곳","img":"https://t1.daumcdn.net/liveboard/mango/f534699c81124a5d82becfbe2d7fa890.png","path":"mango/Bam","isHiddenComment":"false","isDisabledComment":false,"isPublic":true},{"id":"608a64644d31cb16eb995bce","channelKey":"library","serviceKey":"bigissue","publishKey":"608a64644d31cb16eb995bce","consumerId":"1boon","status":"published","description":"두 번의 미라클모닝, 그 후","coverImage":"https://t1.daumcdn.net/liveboard/bigissue/50f6ffbedbf246d4831207db26601bf4.jpeg","serviceTemplate":"listicle","publishTime":1619685770715,"tags":["미라클모닝","모닝루틴","루틴","운동루틴","육아","퇴사","아침식사","유튜브"],"filteredTags":null,"bizKeywords":null,"totalShareCount":null,"shareClickCount":null,"socialIncomingCount":228,"meta":{"_tromm":"society","_app":"harmony","_approvedAt":"1619685774448","_isApproved":"true"},"totalView":302,"recentView":0,"fbCommentCount":0,"useDefaultOpencomment":"true","viewCoverImage":null,"pcCoverImage":"https://t1.daumcdn.net/liveboard/bigissue/50f6ffbedbf246d4831207db26601bf4.jpeg","useLatestOrderComment":"false","cp":null,"viewCoverVideo":null,"summary":[{"title":null,"desc":"<p> <span style=\"color: inherit;\">겉에서 보면 삶이 정상궤도로 보일지라도, 내 안은 끝없이 표류하고 있었다. 직장을 그만두고 모든 걸 다시 시작하고 싶었다. 퇴사 후 늦잠이 아닌 미라클 모닝을 시작하며 나를 되찾아간 이야기다.&nbsp;&nbsp;</span></p>"},{"title":"","desc":"<p>혼돈과 평온의 시기가 무한히 교차되는 삶 속에서 최근 2년간 겪은 혼돈의 시기는 그야말로 역대급이었다. <b>일, 가정, 대인관계 모든 게 뒤죽박죽이었다. </b>무슨 일이 있어도 끝까지 지켜내야 하는 것과 잃어감을 인정하고 익숙해져야 하는 것을 동시에 겪어내는 일은 참으로 가혹했다. ‘육아’와 ‘일’에 관한 이야기다. 출산 후 잠을 이루지 못했다. 아이를 잘 지켜낼 수 있을까 싶어 겁이 났다. 어렵게 잠이 들면 악몽을 꿨다. 보통 아이와 관련된 악몽이었다. 두려움은 날로 늘고 잠을 이루기는 더 어려워졌다. 서서히 우울이라는 감정을 맛보기 시작했다. 잠이 많아 고생하던 시절이 그리웠다. </p>"},{"title":"","desc":"<p> <span style=\"color: inherit;\">어찌어찌 시간은 갔고 1년이 지나 복직했다. 내 자리로 돌아갔으나 내 일은 없었다. 방송은 복직했다고 바로 주어지는 서류와 같지 않았다. 조급한 마음이 들기 시작했다. 얼마 지나지 않아 방송에 투입됐으나 이번엔 내가 문제였다. 머리와 마음과 입이 따로 놀고 있었다. 라디오부스에 들어가 마이크 앞에 앉으면, 세상 무서울 게 없던 이전과 달리 모든 말이 조심스러웠다. ‘내 말이 누군가의 마음을 불편하게 하지 않을까?’, ‘상처가 되지 않을까?’…. 걱정이 끝이 없었다.&nbsp;</span></p>"}],"title":"김혜지 아나운서가 말하는 미라클모닝 실천기!","version":2,"editor":"JwGfFDhhgn","updateTime":1619685770715,"regTime":1619682404217,"titleRaw":"김혜지 아나운서가 말하는 미라클모닝 실천기!","img":"https://t1.daumcdn.net/liveboard/bigissue/50f6ffbedbf246d4831207db26601bf4.jpeg","path":"bigissue/608a64644d31cb16eb995bce","isHiddenComment":"false","isDisabledComment":false,"isPublic":true},{"id":"608a58413c69bd3782375d5e","channelKey":"library","serviceKey":"kncom","publishKey":"608a58413c69bd3782375d5e","consumerId":"1boon","status":"published","description":"","coverImage":"https://t1.daumcdn.net/liveboard/kncom/cc510038e86147639cb46ff62e0e54e2.JPG","serviceTemplate":"listicle","publishTime":1619685548191,"tags":["버뮤다팬츠","버뮤다쇼츠","김나영패션","강민경패션"],"filteredTags":null,"bizKeywords":null,"totalShareCount":null,"shareClickCount":null,"socialIncomingCount":36,"meta":{"_tromm":"fashion","_app":"harmony","_approvedAt":"1619685551977","_isApproved":"true"},"totalView":123,"recentView":0,"fbCommentCount":0,"useDefaultOpencomment":"true","viewCoverImage":null,"pcCoverImage":"","useLatestOrderComment":"false","cp":null,"viewCoverVideo":null,"summary":[{"title":"","desc":"<p style=\"text-align: center; \"><span style=\"color: inherit;\"><br></span></p> \n<p style=\"text-align: center; \"><span style=\"color: inherit;\">작년부터 패션계의 눈길을</span><br></p> \n<p style=\"text-align: center; \">끌었던 아이템이 뭔지 아니??</p> \n<p style=\"text-align: center; \"><br></p> \n<p style=\"text-align: center; \"><br></p> \n<p style=\"text-align: center; \">바로 <b>버뮤다 팬츠</b>야 </p> \n<p style=\"text-align: center; \">버뮤다 팬츠는&nbsp;<span style=\"color: inherit;\">1910년대 버뮤다에서</span></p> \n<p style=\"text-align: center; \"><span style=\"color: inherit;\">영국 군인을&nbsp;</span><span style=\"color: inherit;\">상대로 찻집을 운영하던</span></p> \n<p style=\"text-align: center; \"><span style=\"color: inherit;\">나다니엘 콕슨이&nbsp;</span><span style=\"color: inherit;\">직원들이</span></p> \n<p style=\"text-align: center; \"><span style=\"color: inherit;\">긴 바지가 불편하자&nbsp;</span><span style=\"color: inherit;\">걍 잘라버렸대~~</span></p> \n<p style=\"text-align: center; \"><span style=\"color: inherit;\">SO COOOOL</span></p> \n<p style=\"text-align: center; \"><span style=\"color: inherit;\"><br></span></p> \n<p> </p> \n<p> </p> \n<p> </p> \n<p> </p> \n<p> </p> \n<p> </p> \n<p> </p> \n<p> </p> \n<p> </p> \n<p> </p> \n<p> </p> \n<p> </p>"},{"title":"","desc":"<p style=\"text-align: center; \"><br></p> \n<p style=\"text-align: center; \">버뮤다 팬츠만큼이나</p> \n<p style=\"text-align: center; \">시원한 유래지??</p> \n<p style=\"text-align: center; \"><br></p> \n<p style=\"text-align: center; \"><br></p> \n<p style=\"text-align: center; \">이미 내 마음에 자리한</p> \n<p style=\"text-align: center; \"><b>버뮤다 팬츠 IN MY AREA!</b></p> \n<p style=\"text-align: center; \"><span style=\"color: inherit;\">버뮤다 팬츠 룩 몇가지를 보여줄게</span></p> \n<p style=\"text-align: center; \"><span style=\"color: inherit;\"><br></span></p>"}],"title":"버뮤다 팬츠 IN YOUR AREA!","version":16,"editor":"LMeL2xRJuj","updateTime":1619685548191,"regTime":1619679297307,"titleRaw":"버뮤다 팬츠 IN YOUR AREA!","img":"https://t1.daumcdn.net/liveboard/kncom/cc510038e86147639cb46ff62e0e54e2.JPG","path":"kncom/608a58413c69bd3782375d5e","isHiddenComment":"false","isDisabledComment":false,"isPublic":true},{"id":"608a5b603c69bd3782375dc6","channelKey":"library","serviceKey":"thescoop","publishKey":"608a5b603c69bd3782375dc6","consumerId":"1boon","status":"published","description":"반도체 패권전쟁과 섣부른 위기론","coverImage":"https://t1.daumcdn.net/liveboard/thescoop/5bf82e9006a9407fb1da8b690ce8fb51.JPG","serviceTemplate":"listicle","publishTime":1619685353218,"tags":["더스쿠프","경제주간지","반도체","삼성전자","파운드리","TSMC","인텔","투자"],"filteredTags":null,"bizKeywords":null,"totalShareCount":null,"shareClickCount":null,"socialIncomingCount":0,"meta":{"_tromm":"economy","_app":"harmony"},"totalView":12,"recentView":0,"fbCommentCount":0,"useDefaultOpencomment":"true","viewCoverImage":null,"pcCoverImage":"https://t1.daumcdn.net/liveboard/thescoop/8b63a834f6fa42d2817958564bbe272a.JPG","useLatestOrderComment":"false","cp":null,"viewCoverVideo":null,"summary":[{"title":null,"desc":"<p style=\"text-align: justify; \"><b>삼성전자를 둘러싼 위기론이 불거지고 있다. 세계 각국이 반도체 패권경쟁에 열을 올리고, TSMCㆍ인텔 등 경쟁기업들이 투자 확대를 꾀하고 있지만 삼성전자는 이렇다 할 계획을 내놓지 않고 있어서다. 일부에선 리더의 부재를 지적하며 ‘이재용 사면론’까지 주장하고 있다. 그렇다면 삼성전자가 대규모 투자 계획을 내놓지 않는 게 정말 문제일까. 도리어 합리적 경영 판단이진 않을까. 더스쿠프(The SCOOP)가 ‘기승전-이재용 사면론’과 삼성전자의 현주소를 냉정하게 분석해 봤다.</b></p>"},{"title":"","desc":"<p style=\"text-align: justify; \">“이것이 인프라다. 과거의 인프라를 수리할 게 아니라 오늘날의 인프라를 구축해야 한다.” 지난 4월 12일(현지시간) 미국 백악관에서 열린 ‘반도체 대책회의’. 조 바이든 미국 대통령이 한손에 웨이퍼(반도체를 만드는 주재료ㆍwafer)를 들어 보이며 이같이 선언했다. </p> \n<p style=\"text-align: justify; \"><br></p> \n<p style=\"text-align: justify; \">반도체 품귀현상에 위기감을 느낀 미국이 반도체 공급망 확보에 본격 나서겠다는 뜻이었다. 반도체 산업을 강화하기 위해 500억 달러(약 56조원)를 투입하겠다는 계획도 세웠다. 이날 회의에 삼성전자ㆍ인텔ㆍTSMC 등 19개 반도체 수요ㆍ공급기업을 초청한 것도 ‘미국 내 투자를 확대하라’는 무언의 압박을 보내기 위해서였다. </p> \n<p style=\"text-align: justify; \"><br></p> \n<p style=\"text-align: justify; \">반도체 공급망 확보에 사활을 걸고 있는 건 미국만이 아니다. 같은날 유럽연합(EU)은 36억 유로(약 5조원) 규모의 반도체 투자 계획을 밝힌 데 이어 30일엔 인텔, TSMC와 회담을 가진 것으로 알려졌다. 중국과 대만 정부도 반도체 기업들의 투자를 유인하기 위한 지원정책을 내걸고 있다. 반도체 패권을 차지하기 위한 각국의 경쟁이 치열해지고 있다는 얘기다. </p> \n<p style=\"text-align: justify; \"><br></p> \n<p style=\"text-align: justify; \">이 지점에서 주목할 건 반도체 파운드리(반도체 위탁생산ㆍfoundry) 업체다. 반도체 품귀현상을 해결할 열쇠를 이들 업체들이 쥐고 있어서다. 세계 각국이 반도체 기업 중에서도 특히 파운드리 기업들의 투자를 요구하는 이유도 여기에 있다.[※참고: 파운드리는 반도체 설계도를 받아 위탁생산해주는 반도체 제조전문기업을 말한다.]&nbsp;</p>"},{"title":"","desc":"<p style=\"text-align: justify; \">세계 각국의 요청에 파운드리 업체들도 투자를 확대하고 있다. 세계 1위 종합 반도체 기업 인텔(미국)은 지난 3월 200억 달러(약 23조원) 규모의 투자계획과 함께 파운드리 시장 재진출을 선언했다. 2018년 파운드리 사업을 접은 지 3년여 만이다. 백악관에서의 반도체 대책회의가 끝난 직후엔 “차량용 반도체를 수개월 내에 생산하겠다”며 미국 정부의 투자 요구에 화답하기도 했다. 차량용 반도체는 공급부족 문제가 가장 극심한 제품이다. </p> \n<p style=\"text-align: justify; \"><br></p> \n<p style=\"text-align: justify; \">세계 1위 파운드리 기업 TSMC(대만)도 공격적인 투자에 나섰다. TSMC는 향후 3년간 1000억 달러(약 111조원)를 투자하겠다는 플랜을 발표했다. 미국에 첨단 반도체 공장 6개를 짓는 360억 달러(약 40조원) 규모의 투자 계획에 이은 추가 조치다. 세계 3위 파운드리 기업 글로벌파운드리(미국) 역시 생산능력을 확대하기 위한 14억 달러(약 1조5000억원) 규모의 투자 계획을 공개했다. </p> \n<p style=\"text-align: justify; \"><br></p> \n<p style=\"text-align: justify; \">반면 세계 1위 메모리반도체 기업이자 세계 2위 파운드리 기업인 삼성전자는 아직 묵묵부답이다. 삼성전자 측에 따르면 미국에 170억 달러(약 19조원)를 투자하겠다는 큰 계획은 있다. 하지만 ‘어디에 어떻게 쓸지’ ‘투자 규모를 더 확대할지’ 등의 세부적인 사항은 아직 베일에 싸여 있다. </p> \n<p style=\"text-align: justify; \"><br></p> \n<p style=\"text-align: justify; \">그 때문인지 숱한 미디어에선 삼성전자의 빠른 투자 결정을 촉구하고 있다. 투자가 빈약하거나 타이밍이 늦으면 반도체 패권경쟁에서 밀릴 수 있다는 이유에서다. 일부에선 “대규모 투자가 필요한 상황에서 이재용 삼성전자 부회장이 부재한 탓에 투자가 지연되고 있다”며 ‘사면론’까지 주장하고 있다.&nbsp;</p>"}],"title":"‘기승전-이재용 사면’, 삼성 파운드리는 정말 급한가","version":3,"editor":"LxRMGNygPF","updateTime":1619685353218,"regTime":1619680096205,"titleRaw":"‘기승전-이재용 사면’, 삼성 파운드리는 정말 급한가","img":"https://t1.daumcdn.net/liveboard/thescoop/5bf82e9006a9407fb1da8b690ce8fb51.JPG","path":"thescoop/608a5b603c69bd3782375dc6","isHiddenComment":"false","isDisabledComment":false,"isPublic":true},{"id":"608a5a1f3c69bd3782375d98","channelKey":"enter","serviceKey":"DIATV","publishKey":"608a5a1f3c69bd3782375d98","consumerId":"1boon","status":"published","description":"","coverImage":"https://t1.daumcdn.net/liveboard/DIATV/16b3c0ef0c13450bbedee8c15d0f12d5.JPG","serviceTemplate":"listicle","publishTime":1619685008622,"tags":["제철음식","제철요리","봄제철음식","레시피","반찬","집밥","밑반찬","집반찬"],"filteredTags":null,"bizKeywords":null,"totalShareCount":null,"shareClickCount":null,"socialIncomingCount":0,"meta":{"_tromm":"recipe","_app":"harmony"},"totalView":26,"recentView":0,"fbCommentCount":0,"useDefaultOpencomment":"true","viewCoverImage":"https://t1.daumcdn.net/liveboard/DIATV/16b3c0ef0c13450bbedee8c15d0f12d5.JPG","pcCoverImage":"","useLatestOrderComment":"false","cp":null,"viewCoverVideo":null,"summary":[{"title":null,"desc":"<p style=\"text-align: center;\">제철음식을 먹어야 건강하다는데 </p> \n<p style=\"text-align: center;\">봄에 제철인 요리는 무엇일지 </p> \n<p style=\"text-align: center;\">너무 궁금하지 않나요? </p>"},{"title":"","desc":"<p style=\"text-align: center;\">그런 의미로 오늘은 엄마 손맛 가득한 </p> \n<p style=\"text-align: center;\">제철음식 3가지&nbsp;</p> \n<p style=\"text-align: center;\">구경하러 가봅시다! </p>"},{"title":"","desc":"<div style=\"text-align: center\"> \n <img src=\"https://t1.daumcdn.net/liveboard/emoticon/kakaofriends/v1/niniz2/22.gif\" alt=\"흐물흐물\" class=\"sa-emoticon\"> \n</div>"}],"title":"입맛 사로잡는 봄 제철음식 3가지","version":2,"editor":"nU92msEr6q","updateTime":1619685008622,"regTime":1619679775004,"titleRaw":"입맛 사로잡는 봄 제철음식 3가지","img":"https://t1.daumcdn.net/liveboard/DIATV/16b3c0ef0c13450bbedee8c15d0f12d5.JPG","path":"DIATV/608a5a1f3c69bd3782375d98","isHiddenComment":"false","isDisabledComment":false,"isPublic":true},{"id":"608a1b464d31cb16eb9956f2","channelKey":"library","serviceKey":"kickthecompany","publishKey":"608a1b464d31cb16eb9956f2","consumerId":"1boon","status":"published","description":"브롤 스타즈에 뒤늦게 빠지다","coverImage":"https://t1.daumcdn.net/liveboard/kickthecompany/80a60603ee34434eb10b049ce6273e36.png","serviceTemplate":"listicle","publishTime":1619685008425,"tags":["브롤 스타즈","게임의법칙","회사생활","갓기획"],"filteredTags":null,"bizKeywords":null,"totalShareCount":null,"shareClickCount":null,"socialIncomingCount":2,"meta":{"_tromm":"learning","_app":"harmony"},"totalView":18,"recentView":0,"fbCommentCount":0,"useDefaultOpencomment":"true","viewCoverImage":null,"pcCoverImage":"","useLatestOrderComment":"false","cp":null,"viewCoverVideo":null,"summary":[{"title":null,"desc":"<p><br></p> \n<p><br></p> \n<p><br></p> \n<p><br></p> \n<p>요즘 즐겨하는 게임 중에 ‘브롤 스타즈’라는 모바일 게임이 있다. 이미 유행은 조금 지나갔지만, 늦게 배운 도둑질이 더 무서운 것처럼 ‘즐김’을 넘어서 ‘중독’에 가까운 시간을 투자하고 있다.&nbsp;<span style=\"color: inherit;\">룰은 간단하다. 각기 다른 캐릭터로 무장한 10명의 플레이어가 게임에 접속해서 서로 다른 무기로 상대방을 공격하다가 최후에 남는 1인이 승리하는 게임이다. 한마디로 서바이벌 슈팅게임이다.&nbsp;</span></p> \n<p><span style=\"color: inherit;\"><br></span></p> \n<p><span style=\"color: inherit;\"><br></span></p> \n<p><span style=\"color: inherit;\"><br></span></p> \n<p><span style=\"color: inherit;\">이 게임을 하며 발견한&nbsp;</span><span style=\"color: inherit;\"><b>&nbsp;‘게임의 법칙, 회사 생활의 법칙’</b></span></p> \n<p><br></p> \n<p><br></p> \n<p><br></p> \n<p><br></p> \n<p> </p> \n<p> </p> \n<p> </p> \n<p> </p> \n<p> </p> \n<p> </p> \n<p> </p> \n<p> </p> \n<p> </p> \n<p> </p> \n<p> </p> \n<p> </p> \n<p> </p> \n<p> </p> \n<p> </p> \n<p> </p> \n<p> </p> \n<p> </p> \n<p> </p> \n<p> </p> \n<p> </p> \n<p> </p> \n<p> </p> \n<p> </p> \n<p> </p> \n<p> </p> \n<p> </p> \n<p> </p> \n<p> </p> \n<p> </p> \n<p> </p> \n<p> </p> \n<p> </p> \n<p> </p> \n<p> </p> \n<p> </p> \n<p> </p> \n<p> </p> \n<p> </p> \n<p> </p> \n<p> </p> \n<p> </p> \n<p> </p> \n<p> </p> \n<p> </p> \n<p> </p> \n<p> </p> \n<p> </p> \n<p> </p> \n<p> </p>"},{"title":"","desc":"<p><br></p> \n<p><br></p> \n<p><br></p> \n<p><br></p> \n<p><br></p> \n<p><br></p> \n<p><b>첫째, 싸우지 않으면 성장하지 않는다.</b></p> \n<p><b><br></b></p> \n<p><b><br></b></p> \n<p><span style=\"color: inherit;\">이 게임은 기본적으로 배틀 게임이다. 상대방을 죽이고 살아남는 자가 승리하는 방식이다. 하지만, 이때 몇몇 플레이어들은 적과 싸우기 보다 요리조리 피하고 숨어서 생존하는 전략을 선택한다. 전투를 피하고 오로지 살아남기 위해 버티기만 할 뿐이다. 하지만 이런 플레이어들의 최후는 불 보듯 뻔하다. 결국 상대방을 처치하며 차곡차곡 레벨 업을 한 다른 플레이어들의 먹이감이 될 뿐이다.</span></p> \n<p><span style=\"color: inherit;\"><br></span></p> \n<p>게임에서의 전투는 회사 에서의 일과도 같다. 물론 회사 에서는 늘 하던 일이나 주어진 일만 해도 월급값으로 충분하다. 일을 더 시킬 권리도, 일을 더 해야할 의무도 없다. 하지만 세상일이 어디 정해진 대로만 돌아가는가? </p> \n<p><b>회사 생활을 하다보면, 뜻하지 않게 새로운 일이나 난이도가 높은 일이 주어지는 경우도 있다. </b>이때 이 일을 마다하거나 회피하면 성장은 이루어지지 않는다. <b>실력이 쌓이고 회사에서 성장하는 순간은 늘 어렵고 하기 싫은 일과 맞닿아 있다.</b> 그 일을 성공적으로 수행하던 그렇지 않던 그 일을 끝내는 순간, 경험치가 쌓인다. 그리고 그 경험이 연결되고 연결되어 실력이 되고 노하우가 된다. </p> \n<p><br></p> \n<p><br></p> \n<p>위로 올라갈수록 이것 저것 다 해보고 산전수전 다 겪은 사람은 단단해지고 결국 더 높은 곳으로 올라가 최후의 1인이 된다. 브롤스타즈에서 적들을 처치하며 착실히 레벨업을 달성한 플레이어들 처럼 말이다.</p> \n<p><br></p> \n<p><br></p> \n<p><br></p> \n<p><br></p> \n<p><br></p> \n<p><br></p> \n<p> </p> \n<p> </p> \n<p> </p> \n<p> </p> \n<p> </p> \n<p> </p> \n<p> </p> \n<p> </p> \n<p> </p> \n<p> </p> \n<p> </p> \n<p> </p> \n<p> </p> \n<p> </p> \n<p> </p>"},{"title":"","desc":"<p><br></p> \n<p><br></p> \n<p><br></p> \n<p><br></p> \n<p><br></p> \n<p><b>둘째, 파워 큐브(박스)를 먹어야 성장한다. </b></p> \n<p><br></p> \n<p><br></p> \n<p>게임에서 플레이어가 레벨업을 하는 방법은 두 가지다. 앞서 소개한 것처럼 적을 처치하면 파워가 1만큼 강해진다. 두 명을 처치하면 파워가 2만큼 강해지며 레벨 업을 한다. 이때, 적을 처치하는 방법 외에 파워를 키울 수 있는 방법은 전장 곳곳에 배치되어 있는 박스를 먹는 방법이다. 싸우지 않아도 이 큐브들만 잘 골라 먹어도 적보다 강해지고 전쟁에서 승리할 수 있다.&nbsp;</p> \n<p><br></p> \n<p>회사 생활에서의 파워큐브, 이것의 의미는 자기개발이라고 생각한다.&nbsp;<span style=\"color: inherit;\">가끔, 신입이나 대리때는 일을 잘하다가 어느 정도 직급이 올라가면 B급 플레이어가 되고, 나아가 무능력자가 되며, 결국 퇴물이 되어 퇴사하는 경우를 종종 지켜봤다.&nbsp;</span><span style=\"color: inherit;\"><b>그런 사람들의 경우 대부분 과거의 성공 경험에 매몰되어 있거나, 마음속에 자만심이 자리한 경우가 많았다.</b></span></p> \n<p><span style=\"color: inherit;\"><br></span></p> \n<p><span style=\"color: inherit;\"><br></span></p> \n<p><span style=\"color: inherit;\"><br></span></p> \n<p>‘지금까지 잘해왔으니까 앞으로도 잘할꺼야’, </p> \n<p>‘내가 하던 방식이 맞으니까 하던대로만 하면 되’&nbsp;&nbsp;</p> \n<p>‘나는 잘하니까 공부할 필요없어. 내가 최고인데’ </p> \n<p><br></p> \n<p><br></p> \n<p><br></p> \n<p>세상은 끊임없이 변하고 나를 둘러싼 조직내, 조직 외부의 경쟁자들은 오늘도 손에서 책을 놓치 않고, 각종 아티클을 섭렵하며, 동영상 강의, 오프라인 강연회 등에 참석하며 끊임없이 스스로를 단련해 간다.&nbsp;<span style=\"color: inherit;\">학습하고 자기 개발은 하지 않고, 나를 알아주지 않는 회사만 원망하거나 좋은 게 좋은 거고, 사람이 최고라 생각하며 인간관계만 쌓다가는 나도 모르는 사이 도태되어, 내 주변에 있던 사람들 마저 등을 돌리게 될 지도 모른다.&nbsp;&nbsp;</span><span style=\"color: inherit;\">안주한다는 것은 보이지 않지만, 퇴보하고 있다는 뜻과 같다. 빡센 업무만으로도 충분히 힘들겠지만, 나만의 파워 큐브를 찾아서 매일 매일 나 자신을 높여가는 노력은 언젠가 역치를 뚫고, 그 힘이 발휘되는 날이 올것이다.</span></p> \n<p><br></p> \n<p><br></p> \n<p><br></p> \n<p><br></p> \n<p><br></p> \n<p><br></p> \n<p> </p> \n<p> </p> \n<p> </p> \n<p> </p> \n<p> </p> \n<p> </p> \n<p> </p> \n<p> </p> \n<p> </p> \n<p> </p> \n<p> </p> \n<p> </p> \n<p> </p> \n<p> </p> \n<p> </p> \n<p> </p> \n<p> </p> \n<p> </p> \n<p> </p> \n<p> </p> \n<p> </p> \n<p> </p> \n<p> </p> \n<p> </p> \n<p> </p> \n<p> </p> \n<p> </p> \n<p> </p> \n<p> </p> \n<p> </p> \n<p> </p> \n<p> </p> \n<p> </p> \n<p> </p> \n<p> </p> \n<p> </p> \n<p> </p> \n<p> </p> \n<p> </p> \n<p> </p> \n<p> </p> \n<p> </p> \n<p> </p> \n<p> </p> \n<p> </p> \n<p> </p> \n<p> </p> \n<p> </p> \n<p> </p> \n<p> </p> \n<p> </p> \n<p> </p> \n<p> </p> \n<p> </p> \n<p> </p> \n<p> </p> \n<p> </p> \n<p> </p> \n<p> </p> \n<p> </p> \n<p> </p> \n<p> </p> \n<p> </p> \n<p> </p> \n<p> </p> \n<p> </p> \n<p> </p> \n<p> </p> \n<p> </p> \n<p> </p> \n<p> </p> \n<p> </p> \n<p> </p> \n<p> </p> \n<p> </p> \n<p> </p> \n<p> </p> \n<p> </p> \n<p> </p> \n<p> </p> \n<p> </p> \n<p> </p> \n<p> </p> \n<p> </p> \n<p> </p> \n<p> </p> \n<p> </p> \n<p> </p> \n<p> </p> \n<p> </p> \n<p> </p> \n<p> </p> \n<p> </p>"}],"title":"게임속에서 발견한 회사 생활의 법칙","version":4,"editor":"jm6GVuFWds","updateTime":1619685008425,"regTime":1619663686081,"titleRaw":"게임속에서 발견한 회사 생활의 법칙","img":"https://t1.daumcdn.net/liveboard/kickthecompany/80a60603ee34434eb10b049ce6273e36.png","path":"kickthecompany/608a1b464d31cb16eb9956f2","isHiddenComment":"false","isDisabledComment":false,"isPublic":true},{"id":"6080e8dc40df72357a3f0236","channelKey":"trending","serviceKey":"styleade","publishKey":"6080e8dc40df72357a3f0236","consumerId":"1boon","status":"published","description":"","coverImage":"https://t1.daumcdn.net/liveboard/styleade/1d2917729376487d9db7ffd332201cea.JPG","serviceTemplate":"listicle","publishTime":1619685008076,"tags":["여자연예인패션","서현","윤아","김세정","이시영","정채연","천우희","데이트룩","여친룩"],"filteredTags":null,"bizKeywords":null,"totalShareCount":null,"shareClickCount":null,"socialIncomingCount":20,"meta":{"_tromm":"fashion","_app":"harmony"},"totalView":101,"recentView":0,"fbCommentCount":0,"useDefaultOpencomment":"true","viewCoverImage":"https://t1.daumcdn.net/liveboard/styleade/1d2917729376487d9db7ffd332201cea.JPG","pcCoverImage":"","useLatestOrderComment":"false","cp":null,"viewCoverVideo":null,"summary":[{"title":"천우희","desc":""}],"title":"윤아-김세정이 입은 160만 원대 블라우스","version":4,"editor":"N0TEUMxlmm","updateTime":1619685008076,"regTime":1619060956913,"titleRaw":"윤아-김세정이 입은 160만 원대 블라우스","img":"https://t1.daumcdn.net/liveboard/styleade/1d2917729376487d9db7ffd332201cea.JPG","path":"styleade/6080e8dc40df72357a3f0236","isHiddenComment":"false","isDisabledComment":false,"isPublic":true},{"id":"6088ec434d31cb16eb994e71","channelKey":"trending","serviceKey":"dictlife","publishKey":"6088ec434d31cb16eb994e71","consumerId":"1boon","status":"published","description":"[행동패턴 분석] 12 별자리가 가르쳐주는 진정한 당신의 모습과 감정을 확인하세요.","coverImage":"https://t1.daumcdn.net/liveboard/dictlife/6d9f621c049741758e94d115f5b0862a.JPG","serviceTemplate":"listicle","publishTime":1619684916252,"tags":["별자리성격","심리테스트","운세","무료운세","12별자리","별자리","별자리운세"],"filteredTags":null,"bizKeywords":null,"totalShareCount":null,"shareClickCount":null,"socialIncomingCount":3,"meta":{"_tromm":"fortune","_app":"harmony"},"totalView":49,"recentView":0,"fbCommentCount":0,"useDefaultOpencomment":"true","viewCoverImage":null,"pcCoverImage":"","useLatestOrderComment":"false","cp":null,"viewCoverVideo":null,"summary":[],"title":"5월 8일 어버이날 선물은 어떤 것으로 할지 고민인가요?","version":4,"editor":"5d9NEXXS2G","updateTime":1619684916252,"regTime":1619586115028,"titleRaw":"5월 8일 어버이날 선물은 어떤 것으로 할지 고민인가요?","img":"https://t1.daumcdn.net/liveboard/dictlife/6d9f621c049741758e94d115f5b0862a.JPG","path":"dictlife/6088ec434d31cb16eb994e71","isHiddenComment":"false","isDisabledComment":false,"isPublic":true},{"id":"608901173c69bd37823752cf","channelKey":"trending","serviceKey":"dictlife","publishKey":"608901173c69bd37823752cf","consumerId":"1boon","status":"published","description":"[우문현답] 당신의 마음을 비추는 심리 테스트","coverImage":"https://t1.daumcdn.net/liveboard/dictlife/de50f35b7b0c4a86b9ec5f2199373623.png","serviceTemplate":"listicle","publishTime":1619684902463,"tags":["운세","심리테스트","성격테스트","남녀심리","심리","무료운세","연애심리"],"filteredTags":null,"bizKeywords":null,"totalShareCount":null,"shareClickCount":null,"socialIncomingCount":5,"meta":{"_tromm":"fortune","_app":"harmony"},"totalView":73,"recentView":0,"fbCommentCount":0,"useDefaultOpencomment":"true","viewCoverImage":null,"pcCoverImage":"","useLatestOrderComment":"false","cp":null,"viewCoverVideo":null,"summary":[{"title":null,"desc":"<p>롤러코스터 자리 선택에 따른 <u><b>당신의 성격</b></u>을 확인해 볼 수 있습니다. 스릴있는&nbsp;<span style=\"color: inherit;\">롤러코스터를 좋아하는 사람도, 겁이나서 싫어하는 사람도 꼭 도전해 보세요.</span></p>"},{"title":"당신은 어디 앉았나요?","desc":""}],"title":"롤러코스터 자리 선택으로 알아보는 당신의 진짜 성격","version":8,"editor":"5d9NEXXS2G","updateTime":1619684902463,"regTime":1619591447265,"titleRaw":"롤러코스터 자리 선택으로 알아보는 당신의 진짜 성격","img":"https://t1.daumcdn.net/liveboard/dictlife/de50f35b7b0c4a86b9ec5f2199373623.png","path":"dictlife/608901173c69bd37823752cf","isHiddenComment":"false","isDisabledComment":false,"isPublic":true},{"id":"608a6b834d31cb16eb995c8f","channelKey":"library","serviceKey":"bloter","publishKey":"608a6b834d31cb16eb995c8f","consumerId":"1boon","status":"published","description":"","coverImage":"https://t1.daumcdn.net/liveboard/bloter/b43da84b9ac94b8792eab2685e8399fe.JPG","serviceTemplate":"listicle","publishTime":1619684230729,"tags":["쿠팡","매출채권","매출","현금흐름","블로터"],"filteredTags":null,"bizKeywords":null,"totalShareCount":null,"shareClickCount":null,"socialIncomingCount":0,"meta":{"_tromm":"industry","_app":"harmony"},"totalView":12,"recentView":0,"fbCommentCount":0,"useDefaultOpencomment":"true","viewCoverImage":null,"pcCoverImage":"","useLatestOrderComment":"false","cp":null,"viewCoverVideo":null,"summary":[{"title":null,"desc":"<p>수조원 적자에도 쿠팡의 미래를 무조건 긍정적으로 전망하는 근거 중 하나로는 변화한 ‘현금흐름’이 꼽힌다. 투자가 많은 탓에 지출이 많을 뿐이지 영업활동에서는 이미 이익이 나고 있다는 것이다. 결국 그동안 출혈은 컸지만 어쨌든 수익모델을 만드는 데는 성공했고, 앞으로 수익성도 좋아질 테니 괜찮다는 논리다. </p> \n<p><br></p> \n<p>물론 앞으로 쿠팡의 수익성이 좋아질 것이라는 데에는 업계에서도 큰 이견이 없다. 다만 수익성 개선의 속도와 폭이 어떨지가 관건이다. 그렇다면 현금흐름으로 본 쿠팡의 현재 모습은 어떨까. </p> \n<p><br></p> \n<p><b>매출 14조 차세대 유통 공룡 </b></p> \n<p><br></p> \n<p>우선 쿠팡의 지난해 실적을 살펴보자. 쿠팡은 매출액 14조원을 거두며 국내 유통시장 차세대 공룡으로 자라났다. 무엇보다 전년 7조2000억원과 비교해 무려 두 배 가까이 매출을 늘리며 엄청난 성장 속도를 보였다. 성장세를 보면 기존 유통 대기업들이 왜 위기감을 느끼고 이커머스(e-Commerce)시장에 ‘올인’하는지 알 수 있다. 이마트의 지난해 매출액은 22조원으로 쿠팡이 따라잡는 모습도 충분히 상상 가능하다.</p> \n<p> </p> \n<p> </p> \n<p> </p>"},{"title":"","desc":"<p>잘 알려졌다시피 매출은 늘었지만 영업적자는 지속됐다. 전년 대비 적자 폭이 2000억원가량 줄긴 했지만 여전히 5500억원 규모의 큰 손실을 냈다. 벌어들이는 돈 보다 쓰는 돈이 더 많은 상황인 것이다. </p> \n<p><br></p> \n<p>구체적으로 살펴보면 쿠팡의 매출액에서 차감되는 항목은 ‘매출원가’와 ‘영업 일반관리비’ 두 개다. 쿠팡의 매출원가는 상품매출원가 및 배송관련 원가로, 배송서비스를 제공하며 부담하는 운송원가 등이 여기에 포함돼 있다. ‘영업 일반관리비’는 매출원가를 제외한 모든 비용을 의미하며, 풀필먼트센터 운영비용, 고객 서비스 관련 비용, 결제대행 수수료, 기술 인프라 및 온라인 플랫폼 유지보수 비용 등이다. </p> \n<p><br></p> \n<p>지난해 쿠팡의 매출원가는 전년 대비 약 2배 가까이 늘어난 11조6000억원으로 집계됐다. 매출이 대폭 증가하며 자연스레 매출원가도 크게 늘어났다. 매출원가율은 83.2%로 전년과 동일한 것으로 나타났다. 제조업의 경우 일반적으로 매출이 늘면 규모의 경제를 통해 원가가 절감되는 효과가 발생한다. 그러나 쿠팡의 경우 저마진 구조의 유통업 특성상 원가절감 효과는 전혀 발생하지 않은 것으로 분석된다. </p> \n<p><br></p> \n<p>영업 일반관리비로는 2조9000억원을 썼다. 전년 1조9000억원보다 1조원 지출이 늘었다. 매출액 대비 관리비용 비율은 20.8%로 전년 26.9%와 비교해 약 6% 포인트 개선됐다. 쿠팡의 영업손실 규모가 줄어든 것은 관리비 비중 감소 덕분으로 분석된다. </p> \n<p><br></p> \n<p><b>'미지급금·매입채무'로 늘린 현금흐름 </b></p> \n<p><br></p> \n<p>그렇다면 기업 회계의 ‘속살’로도 불리는 쿠팡의 현금흐름은 과연 어떤지 살펴보자. 현금흐름표는 재무제표에서 유일하게 현금을 기준으로 작성되기 때문에 회계법으로 인한 왜곡효과가 최대한 완화돼 나타난다. 이익이 나더라도 아직 현금을 받지 못했을 경우도 있고, 반대로 비용지출이 발생하더라도 현금은 빠져나가지 않는 경우도 있다.</p> \n<p> </p> \n<p> </p> \n<p> </p> \n<p> </p> \n<p> </p> \n<p> </p>"}],"title":"쿠팡 현금흐름표 뜯어보니...흑자는 외상값 늘린 덕?","version":2,"editor":"mcf08ZLPCB","updateTime":1619684230729,"regTime":1619684227632,"titleRaw":"쿠팡 현금흐름표 뜯어보니...흑자는 외상값 늘린 덕?","img":"https://t1.daumcdn.net/liveboard/bloter/b43da84b9ac94b8792eab2685e8399fe.JPG","path":"bloter/608a6b834d31cb16eb995c8f","isHiddenComment":"false","isDisabledComment":false,"isPublic":true},{"id":"6088f0b03c69bd37823751d2","channelKey":"library","serviceKey":"DIMAZINE","publishKey":"6088f0b03c69bd37823751d2","consumerId":"1boon","status":"published","description":"원피스 맛집 잇미샤로 꾸민 유이, 지수의 원피스룩","coverImage":"https://t1.daumcdn.net/liveboard/DIMAZINE/0d519867257b46d29713330f844ed4d6.jpg","serviceTemplate":"listicle","publishTime":1619684069294,"tags":["잇미샤","itmichaa","유이원피스","온앤오프유이","지수원피스","원피스추천","원피스맛집","데이트룩"],"filteredTags":null,"bizKeywords":null,"totalShareCount":null,"shareClickCount":null,"socialIncomingCount":560,"meta":{"_tromm":"fashion","_app":"harmony","_approvedAt":"1619684072521","_isApproved":"true"},"totalView":843,"recentView":0,"fbCommentCount":0,"useDefaultOpencomment":"true","viewCoverImage":null,"pcCoverImage":"https://t1.daumcdn.net/liveboard/DIMAZINE/0d519867257b46d29713330f844ed4d6.jpg","useLatestOrderComment":"false","cp":null,"viewCoverVideo":null,"summary":[{"title":null,"desc":"<p style=\"text-align: center; \"><br></p> \n<p style=\"text-align: center; \">이번주 ‘온앤오프’ 모두들 보셨나요? </p> \n<p style=\"text-align: center; \">건강미의 주인공 </p> \n<p style=\"text-align: center; \">유이의 바디 프로필 도전 과정을 </p> \n<p style=\"text-align: center; \">만날 수 있었는데요. </p> \n<p style=\"text-align: center; \"><br></p> \n<p style=\"text-align: center; \">이와 함께 뮤지컬 콘셉트의 </p> \n<p style=\"text-align: center; \">영상 촬영 현장이 공개되며 </p> \n<p style=\"text-align: center; \">유이의 춤을 제대로 감상할 수 있었습니다.</p> \n<p style=\"text-align: center; \"> </p>"},{"title":"","desc":"<p style=\"text-align: center;\"><br></p> \n<p style=\"text-align: center;\">‘온앤오프’에서 보고 예쁘다고 난리났던 </p> \n<p style=\"text-align: center;\">유이의 영상 촬영은 </p> \n<p style=\"text-align: center;\">페미닌룩 브랜드 잇미샤와 </p> \n<p style=\"text-align: center;\">함께했는데요. </p> \n<p style=\"text-align: center;\"><br></p> \n<p style=\"text-align: center;\">전설적인 보컬 그룹&nbsp;<span style=\"color: inherit;\">템테이션의</span></p> \n<p style=\"text-align: center;\">‘The way you do the things you do’ </p> \n<p style=\"text-align: center;\">노래와 함께 </p> \n<p style=\"text-align: center;\">19명의 뮤지컬 배우가 </p> \n<p style=\"text-align: center;\">멋진 퍼포먼스를 선보였습니다. </p> \n<p style=\"text-align: center;\"><br></p> \n<p style=\"text-align: center;\">뮤지컬 ‘오페라의 유령’의 </p> \n<p style=\"text-align: center;\">홍세정 안무 감독이 참여해 </p> \n<p style=\"text-align: center;\">한층 퀄리티를 높였는데요. </p> \n<p style=\"text-align: center;\"><br></p> \n<p style=\"text-align: center;\">‘온앤오프’에서 본 것처럼 </p> \n<p style=\"text-align: center;\">마지막까지 밝고 활기찬 </p> \n<p style=\"text-align: center;\">유이 특유의 에너지를 느낄 수 있었죠.</p> \n<p style=\"text-align: center;\"> </p> \n<p style=\"text-align: center;\"> </p> \n<p style=\"text-align: center;\"> </p>"}],"title":"온앤오프 유이 블랙핑크 지수의 원피스 어디꺼?","version":5,"editor":"Y7tz5w2yrx","updateTime":1619684069294,"regTime":1619587248149,"titleRaw":"온앤오프 유이 블랙핑크 지수의 원피스 어디꺼?","img":"https://t1.daumcdn.net/liveboard/DIMAZINE/0d519867257b46d29713330f844ed4d6.jpg","path":"DIMAZINE/6088f0b03c69bd37823751d2","isHiddenComment":"false","isDisabledComment":false,"isPublic":true},{"id":"608a67fd18c79f2de601319e","channelKey":"library","serviceKey":"zigbang","publishKey":"608a67fd18c79f2de601319e","consumerId":"1boon","status":"published","description":"절세의 신 104화","coverImage":"https://t1.daumcdn.net/liveboard/zigbang/6fd6e1d5bcff4f3ead223c222467bfd8.JPG","serviceTemplate":"videoview","publishTime":1619683810448,"tags":["직방","직방tv","절세의신","제네시스박","절세","부동산세금","매도","증여","임대주택"],"filteredTags":null,"bizKeywords":null,"totalShareCount":null,"shareClickCount":null,"socialIncomingCount":0,"meta":{"_tromm":"real_estate","_app":"harmony"},"totalView":14,"recentView":0,"fbCommentCount":0,"useDefaultOpencomment":"true","viewCoverImage":null,"pcCoverImage":"","useLatestOrderComment":"false","cp":null,"viewCoverVideo":"https://www.youtube.com/embed/EkkgD6zkVvI","summary":[{"title":null,"desc":"<p style=\"text-align: center; \">-</p> \n<p style=\"text-align: center; \">직방TV 절세의 신,&nbsp;</p> \n<p style=\"text-align: center; \">제네시스박입니다.</p> \n<p style=\"text-align: center; \"><br></p> \n<p style=\"text-align: center; \">요즘 늘어난 세금 때문에</p> \n<p style=\"text-align: center; \">다주택자 분들 걱정이</p> \n<p style=\"text-align: center; \">이만저만 아니시죠?</p> \n<p style=\"text-align: center; \"><br></p> \n<p style=\"text-align: center; \">이런 저런 규제 때문에</p> \n<p style=\"text-align: center; \">쉽게 매물을 팔지도</p> \n<p style=\"text-align: center; \">그렇다고 보유하기도</p> \n<p style=\"text-align: center; \">쉽지않은데요~</p> \n<p style=\"text-align: center; \"><br></p> \n<p style=\"text-align: center; \">그렇다면 지금&nbsp;</p> \n<p style=\"text-align: center; \">다주택자가 취해야하는</p> \n<p style=\"text-align: center; \">행동은 뭐가있을까요?</p> \n<p style=\"text-align: center; \"><br></p> \n<p style=\"text-align: center; \">저 제네시스가 한 번&nbsp;</p> \n<p style=\"text-align: center; \">정리해봤습니다!</p> \n<p style=\"text-align: center; \"><br></p> \n<p style=\"text-align: center; \">자세히 알아보도록 할까요?</p> \n<p style=\"text-align: center; \">지금 바로 ‘절세의 신 104화’를</p> \n<p style=\"text-align: center; \">시청하세요!</p> \n<p style=\"text-align: center; \"><br></p> \n<p style=\"text-align: center; \">-</p> \n<p style=\"text-align: center; \"><b>타임라인</b></p> \n<p style=\"text-align: center; \">0:00 하이라이트 &amp; 인트로</p> \n<p style=\"text-align: center; \">00:32 오늘의 주제는?&nbsp;</p> \n<p style=\"text-align: center; \">01:44 다주택자의 매도전략!</p> \n<p style=\"text-align: center; \">02:36 세법상 장기임대주택은?</p> \n<p style=\"text-align: center; \">05:51 매도시 또다른 팁!</p> \n<p style=\"text-align: center; \">09:47 최종 1주택 유의하세요!</p> \n<p style=\"text-align: center; \">11:09 임대주택사업자 등록?!</p> \n<p style=\"text-align: center; \">13:17 증여도 알아야 합니다!</p> \n<p style=\"text-align: center; \"><br></p> \n<p style=\"text-align: center; \">-</p> \n<p style=\"text-align: center; \"><b>유튜브 최고의 절세 강의,&nbsp;</b></p> \n<p style=\"text-align: center; \">제네시스박의 '절세의 신'</p> \n<p style=\"text-align: center; \"><b>\uD83D\uDC49 매주 목요일 오후 5시&nbsp;</b></p> \n<p style=\"text-align: center; \">[직방TV]에서 공개</p> \n<p style=\"text-align: center; \"><br></p> \n<p style=\"text-align: center; \"><br></p> \n<p style=\"text-align: center; \"><br></p>"}],"title":"다주택자라면 꼭 알아야 하는 절세전략!","version":2,"editor":"YDQwKNGepr","updateTime":1619683810448,"regTime":1619683325141,"titleRaw":"다주택자라면 꼭 알아야 하는 절세전략!","img":"https://t1.daumcdn.net/liveboard/zigbang/6fd6e1d5bcff4f3ead223c222467bfd8.JPG","path":"zigbang/608a67fd18c79f2de601319e","isHiddenComment":"false","isDisabledComment":false,"isPublic":true},{"id":"608a69ab3c69bd3782375f28","channelKey":"library","serviceKey":"slownews","publishKey":"80561","consumerId":"1boon","status":"published","description":"이렇게 부려먹고 '프리랜서'라고 우기면 곤란합니다....","coverImage":"https://t1.daumcdn.net/liveboard/slownews/719284046baf4bcb88d61afa66649ed0.jpg","serviceTemplate":"listicle","publishTime":1619683793522,"tags":["방송작가","프리랜서","노동자","근로자"],"filteredTags":null,"bizKeywords":null,"totalShareCount":null,"shareClickCount":null,"socialIncomingCount":112,"meta":{"_tromm":"society","_app":"harmony","_approvedAt":"1619683796640","_isApproved":"true"},"totalView":184,"recentView":0,"fbCommentCount":0,"useDefaultOpencomment":"true","viewCoverImage":null,"pcCoverImage":"https://t1.daumcdn.net/liveboard/slownews/3402c0212339457fbaa056cdf0f12602.jpeg","useLatestOrderComment":"false","cp":null,"viewCoverVideo":null,"summary":[{"title":null,"desc":"<p>머릿속으로 떠올려 보자. 당신이 텔레비전으로 보고 있는 방송프로그램을. 혹은 스마트폰으로 보고 있을 그 프로그램을. 뉴스 브리핑 등 정치, 경제, 시사 프로그램이 나오는 프로그램이라면 좋겠다.</p>"},{"title":"","desc":"<p>생방송 아침 프로그램을 하는 스튜디오에 와 있다. 프로그램 제목이 벽에 걸려 있다. 벽 뒤편은 텅 비어 있다. 미리 조정을 맞춰놓은 조명 아래 무대는 대낮같이 밝다. 분장을 마친 아나운서 또는 프리랜서 연예인들이 출연자석에 있다. 기술 보조가 와서 무선 마이크 성량 등을 체크한다. 진행 소품이 챙겨진다. 무대를 중심으로 3대 이상의 카메라가 촬영을 시작한다.</p>"},{"title":"","desc":"<p>부조정실 안에서 PD가 신호를 보낸다. 생방송이 시작된다. 준비해 둔 타이틀이 웅장한 음악과 함께 등장한다. 거리를 두고 앉은 패널들이 말하기 시작한다. 출연자 자막 및 주요 내용을 요약한 발언이 자막으로 나간다. 무대 위 출연진들은 각종 차트를 위에 올려놓고 말하기 시작한다. 오디오 효과음과 함께 ‘자 이제 현장으로 가겠습니다’라고 말하면 준비해둔 영상으로 넘어간다. 코너를 담당한 PD들과 작가들이 순서를 기다린다.</p>"}],"title":"방송작가가 ‘노동자’인 이유","version":2,"editor":"7ymYqXnAQu","updateTime":1619683793522,"regTime":1619683755478,"titleRaw":"방송작가가 ‘노동자’인 이유","img":"https://t1.daumcdn.net/liveboard/slownews/719284046baf4bcb88d61afa66649ed0.jpg","path":"slownews/80561","isHiddenComment":"false","isDisabledComment":false,"isPublic":true},{"id":"608a69b518c79f2de60131d5","channelKey":"sports","serviceKey":"zoollook","publishKey":"608a69b518c79f2de60131d5","consumerId":"1boon","status":"published","description":"","coverImage":"https://t1.daumcdn.net/liveboard/zoollook/4baa833309ec4732a7d1866faf842f57.png","serviceTemplate":"listicle","publishTime":1619683768019,"tags":["엠스플뉴스","이진영","조동화","추신수","SSG랜더스","KBO"],"filteredTags":null,"bizKeywords":null,"totalShareCount":null,"shareClickCount":null,"socialIncomingCount":260,"meta":{"_tromm":"baseball","_app":"harmony","_approvedAt":"1619683770810","_isApproved":"true"},"totalView":515,"recentView":0,"fbCommentCount":0,"useDefaultOpencomment":"true","viewCoverImage":null,"pcCoverImage":"","useLatestOrderComment":"false","cp":null,"viewCoverVideo":null,"summary":[],"title":"형저메는 없다! 추신수, 이진영-조동화 코치에 무한 질문","version":2,"editor":"efmuvEzJXj","updateTime":1619683768019,"regTime":1619683764682,"titleRaw":"형저메는 없다! 추신수, 이진영-조동화 코치에 무한 질문","img":"https://t1.daumcdn.net/liveboard/zoollook/4baa833309ec4732a7d1866faf842f57.png","path":"zoollook/608a69b518c79f2de60131d5","isHiddenComment":"false","isDisabledComment":false,"isPublic":true},{"id":"608a69443c69bd3782375f1d","channelKey":"enter","serviceKey":"MOVIST","publishKey":"608a69443c69bd3782375f1d","consumerId":"1boon","status":"published","description":"무비스트 추천, 5월 첫째 주","coverImage":"https://t1.daumcdn.net/liveboard/MOVIST/6bae6397a71940dabb6321db480efb75.png","serviceTemplate":"swipe","publishTime":1619683656250,"tags":[],"filteredTags":null,"bizKeywords":null,"totalShareCount":null,"shareClickCount":null,"socialIncomingCount":4,"meta":{"_tromm":"movie","_app":"harmony"},"totalView":10,"recentView":0,"fbCommentCount":0,"useDefaultOpencomment":"true","viewCoverImage":null,"pcCoverImage":"","useLatestOrderComment":"false","cp":null,"viewCoverVideo":null,"summary":[{"title":"무비스트","desc":"영화,기사"}],"title":"새로나온 웹툰이 궁금해? 금주의 신작!","version":2,"editor":"wRXWYRclbj","updateTime":1619683656250,"regTime":1619683652195,"titleRaw":"새로나온 웹툰이 궁금해? 금주의 신작!","img":"https://t1.daumcdn.net/liveboard/MOVIST/6bae6397a71940dabb6321db480efb75.png","path":"MOVIST/608a69443c69bd3782375f1d","isHiddenComment":"false","isDisabledComment":false,"isPublic":true},{"id":"608a5e5a3c69bd3782375e27","channelKey":"enter","serviceKey":"sbsnoriter","publishKey":"608a5e5a3c69bd3782375e27","consumerId":"1boon","status":"published","description":"","coverImage":"https://t1.daumcdn.net/liveboard/sbsnoriter/a56f9fa63cf44c368693fce16339c595.JPG","serviceTemplate":"listicle","publishTime":1619683505288,"tags":["동상이몽","김성은","정조국","SBS"],"filteredTags":null,"bizKeywords":null,"totalShareCount":null,"shareClickCount":null,"socialIncomingCount":2382,"meta":{"_tromm":"enter_general","_app":"harmony","_approvedAt":"1.619683509481E12","_isApproved":"true"},"totalView":4724,"recentView":0,"fbCommentCount":0,"useDefaultOpencomment":"true","viewCoverImage":null,"pcCoverImage":"","useLatestOrderComment":"false","cp":null,"viewCoverVideo":null,"summary":[{"title":"","desc":"<p style=\"text-align: center;\">동상이몽 새 <b>운명부부</b>로 합류한</p> \n<p style=\"text-align: center;\">김성은♥정조국</p>"},{"title":"","desc":"<div style=\"text-align: center\"> \n <img src=\"https://t1.daumcdn.net/liveboard/emoticon/kakaofriends/v2/10014/emot_718.gif\" alt=\"짜잔\" class=\"sa-emoticon\"> \n</div>"},{"title":"","desc":"<p style=\"text-align: center;\">연하는 남자로 안 보이던 김성은이</p> \n<p style=\"text-align: center;\">한 살 연하 정조국을 만나고</p> \n<p style=\"text-align: center;\">한 번도 동생으로 보인 적이 없다며</p> \n<p style=\"text-align: center;\">인터뷰 시작부터 애정 뿜뿜~♥</p>"}],"title":"연예계 활동과 결혼을 맞바꿀 수 있다는 여배우","version":9,"editor":"QcXJJemazu","updateTime":1619683618436,"regTime":1619680858853,"titleRaw":"연예계 활동과 결혼을 맞바꿀 수 있다는 여배우","img":"https://t1.daumcdn.net/liveboard/sbsnoriter/a56f9fa63cf44c368693fce16339c595.JPG","path":"sbsnoriter/608a5e5a3c69bd3782375e27","isHiddenComment":"false","isDisabledComment":false,"isPublic":true}],"pagingInfo":{"currentPageIndex":1,"totalPageCount":15524,"totalRecordCount":310466,"pageSize":20,"hasPrev":false,"hasNext":true}}