{"status":{"code":200,"name":"OK"},"data":[{"id":"600b84b28c31e10ed1c87fa2","channelKey":"trending","serviceKey":"awesome","publishKey":"600b84b28c31e10ed1c87fa2","consumerId":"1boon","status":"published","description":"이 영상 하나에 가족들이 그렇게 난리라구요?????","coverImage":"https://t1.daumcdn.net/liveboard/awesome/941ad8712ebf44ab8b59be282ff4fa2f.png","serviceTemplate":"listicle","publishTime":1611529486014,"tags":["한국","외국인","러시아","산책","가족","이유","영상","문화"],"filteredTags":null,"bizKeywords":["영상","러시아","가족","문화","한국","이유","산책","외국인"],"totalShareCount":null,"shareClickCount":null,"socialIncomingCount":0,"meta":{"_tromm":"humor","_app":"harmony"},"totalView":3,"recentView":0,"fbCommentCount":0,"useDefaultOpencomment":"true","viewCoverImage":null,"pcCoverImage":"https://t1.daumcdn.net/liveboard/awesome/941ad8712ebf44ab8b59be282ff4fa2f.png","useLatestOrderComment":"false","cp":null,"viewCoverVideo":null,"summary":[{"title":"한국사는 외국인이 찍은 밤 산책 영상에 가족들이 난리난 이유","desc":"#외국인 #외국인반응 #해외반응\n딸을 한국에 보낸 러시아 부모님이 걱정이 많으셨는데요!\n\n그 걱정을 한방에 싹 날려줄 영상을 소피아님께서 찍었다고 합니다!\n\n오늘은 러시아에서 오신 소피아님께서 한국의 밤거리에 부모님이\n\n놀랐던 이유에 대해서 말씀해 주셨습니다.\n\n영상이 궁금하시다면, 지금 바로 보러~가시죠!\n\n♥영상이 재미있으셨다면 구독 좋아요 누르는 센스♥\n☞추천하는 영상이나 도전해봤으면 하는 것들이 있으면 '댓글'로 남겨주세요!\n\n※어썸스토리의 또 다른 재밌는 영상들도 만나보세요!\n\n출연 및 제휴 문의 : wognswotjr@gmail.com"},{"title":"&lt; 소피아가 부모님께 보낸 영상 &gt;","desc":""}],"title":"한국사는 외국인이 찍은 밤 산책 영상에 가족들이 난리난 이유","version":9,"editor":"WhgZSPosPm","updateTime":1611529486014,"regTime":1611367602261,"titleRaw":"한국사는 외국인이 찍은 밤 산책 영상에 가족들이 난리난 이유","img":"https://t1.daumcdn.net/liveboard/awesome/941ad8712ebf44ab8b59be282ff4fa2f.png","path":"awesome/600b84b28c31e10ed1c87fa2","isHiddenComment":"false","isDisabledComment":false,"isPublic":true},{"id":"600d93588c31e10ed1c88235","channelKey":"enter","serviceKey":"feelthemovie","publishKey":"600d93588c31e10ed1c88235","consumerId":"1boon","status":"published","description":"중국 영화계 선호도 1위 차지한 한국배우 클라라 근황","coverImage":"https://t1.daumcdn.net/liveboard/feelthemovie/6d44216d3a8046e887b1a836a13ab470.JPG","serviceTemplate":"listicle","publishTime":1611529212239,"tags":["클라라","영화뉴스","필더무비","송중기","워킹걸"],"filteredTags":null,"bizKeywords":["워킹걸","영화뉴스"],"totalShareCount":null,"shareClickCount":null,"socialIncomingCount":0,"meta":{"_tromm":"movie","_app":"harmony"},"totalView":39,"recentView":0,"fbCommentCount":0,"useDefaultOpencomment":"true","viewCoverImage":null,"pcCoverImage":"https://t1.daumcdn.net/liveboard/feelthemovie/3a8a83fae058451185ebddf9734d9205.JPG","useLatestOrderComment":"false","cp":null,"viewCoverVideo":null,"summary":[{"title":"","desc":"<div style=\"text-align: center\"> \n <img src=\"https://t1.daumcdn.net/liveboard/emoticon/kakaofriends/v2/10009/thum_316_x3.png\" alt=\"뭐더라\" class=\"sa-emoticon\"> \n</div>"},{"title":null,"desc":"<p>7,8년 전만 해도 연예계에서 최고로 핫한 스타였는데…어느 순간 대중의 뇌리에서 잊힌 듯한 배우가 있다.</p> \n<p> </p> \n<p>그래도 이 배우의 이름만 이야기하면…</p>"},{"title":"","desc":"<div style=\"text-align: center\"> \n <img src=\"https://t1.daumcdn.net/liveboard/emoticon/kakaofriends/v2/10009/thum_003_x3.png\" alt=\"헬로우\" class=\"sa-emoticon\"> \n</div> \n<div style=\"text-align: center\"> \n <b>아!</b> \n</div>"}],"title":"한국에서는 더이상 활동안하는데…중국가서 엄청 성공해 1위찍은 배우","version":3,"editor":"Kpou0mcYXV","updateTime":1611529212239,"regTime":1611502424077,"titleRaw":"한국에서는 더이상 활동안하는데…중국가서 엄청 성공해 1위찍은 배우","img":"https://t1.daumcdn.net/liveboard/feelthemovie/6d44216d3a8046e887b1a836a13ab470.JPG","path":"feelthemovie/600d93588c31e10ed1c88235","isHiddenComment":"false","isDisabledComment":true,"isPublic":true},{"id":"600d7a8b423bc27f2c926d60","channelKey":"enter","serviceKey":"1MinNFLX","publishKey":"600d7a8b423bc27f2c926d60","consumerId":"1boon","status":"published","description":"하나씨 추여사님 벌써 그리워요 엉엉","coverImage":"https://t1.daumcdn.net/liveboard/1MinNFLX/66846bffa4b14dd1b1d47b2103f38dc5.jpeg","serviceTemplate":"listicle","publishTime":1611529212129,"tags":["경이로운 소문","경이로운소문","세정","김세정","염혜란","추매옥","추여사","김세정 인터뷰","염혜란 인터뷰"],"filteredTags":null,"bizKeywords":["세정","경이로운소문"],"totalShareCount":null,"shareClickCount":null,"socialIncomingCount":1,"meta":{"_tromm":"movie","_app":"harmony"},"totalView":16,"recentView":0,"fbCommentCount":0,"useDefaultOpencomment":"true","viewCoverImage":null,"pcCoverImage":"https://t1.daumcdn.net/liveboard/1MinNFLX/4cddca4531044eeba534088abe7548cd.jpeg","useLatestOrderComment":"false","cp":null,"viewCoverVideo":null,"summary":[{"title":null,"desc":"<p><b>[키워드 인터뷰]</b></p>"},{"title":"","desc":"<div style=\"text-align: center\"> \n <img src=\"https://t1.daumcdn.net/liveboard/emoticon/kakaofriends/v3/ryan/006.gif\" alt=\"야광봉\" class=\"sa-emoticon\"> \n</div>"},{"title":"","desc":"<p>왔다 왔다!!!&nbsp;<span style=\"color: inherit;\">'경이로운 소문'의 조병규, 유준상에 이어 김세정과 염혜란의 인터뷰도 데려왔다.&nbsp;</span></p> \n<p><br></p> \n<p>인간 비타민 김세정과 수줍은 듯 센스 넘치는 염혜란의 키워드 인터뷰, '경이로운 소문' 비하인드 스토리부터 두 사람의 개인사까지 듬뿍 담았다.&nbsp;</p> \n<p><br></p> \n<p>'경이로운 소문'의 도하나, 김세정부터 출발!&nbsp;</p>"}],"title":"세정이 EXO 세훈을 형님이라 불렀던 이유","version":16,"editor":"aVrPyCRlYk","updateTime":1611529212129,"regTime":1611496075863,"titleRaw":"세정이 EXO 세훈을 형님이라 불렀던 이유","img":"https://t1.daumcdn.net/liveboard/1MinNFLX/66846bffa4b14dd1b1d47b2103f38dc5.jpeg","path":"1MinNFLX/600d7a8b423bc27f2c926d60","isHiddenComment":"false","isDisabledComment":false,"isPublic":true},{"id":"600bf98c8c31e10ed1c88099","channelKey":"library","serviceKey":"thevivid","publishKey":"600bf98c8c31e10ed1c88099","consumerId":"1boon","status":"published","description":"","coverImage":"https://t1.daumcdn.net/liveboard/thevivid/e62604b4102f467b8bb7fa8862b9f0c2.JPG","serviceTemplate":"listicle","publishTime":1611529211570,"tags":["수출","김치","한국","딸기","한식","한국음식","중국","일본"],"filteredTags":null,"bizKeywords":["김치","한식","수출","딸기","중국","일본","한국음식","한국"],"totalShareCount":null,"shareClickCount":null,"socialIncomingCount":1,"meta":{"_tromm":"food","_app":"harmony"},"totalView":12,"recentView":0,"fbCommentCount":0,"useDefaultOpencomment":"true","viewCoverImage":null,"pcCoverImage":"https://t1.daumcdn.net/liveboard/thevivid/e62604b4102f467b8bb7fa8862b9f0c2.JPG","useLatestOrderComment":"false","cp":null,"viewCoverVideo":null,"summary":[{"title":null,"desc":"<p>코로나로 세계 경제가 어려움을 겪으면서 작년 우리나라 수출도 큰 타격을 입었다. 그런데 식품은 예외다. 작년 우리나라 농식품 수출이 사상 최대를 기록했다고 한다. 어떤 배경이 있는지 알아봤다. </p> \n<p> </p> \n<p><br></p> \n<p><b>◇대미 농식품 수출 33% 급증 </b></p>"},{"title":"","desc":"<p><br></p> \n<p>농림축산식품부에 따르면, 작년 우리나라 농식품 수출액은 1년 전보다 7.7% 증가한 75억7000만달러로 사상 최대치를 기록했다. 과일 같은 신선 농산물과 라면 같은 가공식품 수출이 둘 다 늘었다. 신선 농산물은 14억3000만달러, 가공식품은 61억4000만달러 실적을 기록했다. </p> \n<p> </p> \n<p><br></p> \n<p>수출 1위국은 미국이다. 대(對)미국 수출이 12억1000만달러로 13년만에 중국(11억4000만달러)을 제치고 우리나라 농식품 수출 1위국에 올라섰다. 작년 대미 농식품 수출은 1년 전 보다 38% 급증해 대중 수출 증가율(2.9%)을 크게 앞질렀다. </p> \n<p><br></p> \n<p> </p> \n<p>농식품 수출은 전체 수출 실적과 비교하면 증가폭이 두드러진다. 작년 우리나라 전체 연간 수출액은 5128억5000만달러로 1년 전보다 5.4% 줄었다. 그런데 ‘K푸드’ 수출은 오히려 늘었다. </p> \n<p><br></p> \n<p> </p> \n<p><b>◇김치 수출은 절반이 일본 </b></p>"}],"title":"13년 만 중국 제쳤다, 작년 한국 식품 가장 많이 구매한 나라","version":2,"editor":"hbNJGl5Rtq","updateTime":1611529211570,"regTime":1611397516599,"titleRaw":"13년 만 중국 제쳤다, 작년 한국 식품 가장 많이 구매한 나라","img":"https://t1.daumcdn.net/liveboard/thevivid/e62604b4102f467b8bb7fa8862b9f0c2.JPG","path":"thevivid/600bf98c8c31e10ed1c88099","isHiddenComment":"false","isDisabledComment":false,"isPublic":true},{"id":"600bf3ad7f352620e507b15b","channelKey":"library","serviceKey":"thevivid","publishKey":"600bf3ad7f352620e507b15b","consumerId":"1boon","status":"published","description":"","coverImage":"https://t1.daumcdn.net/liveboard/thevivid/5b7e2c453fa544e0b854c7eff961f1c9.jpg","serviceTemplate":"listicle","publishTime":1611529211488,"tags":["손톱","국산","손톱깎이","보카스","발각질제거","헹켈","쌍둥이칼","삼성"],"filteredTags":null,"bizKeywords":["손톱깎이","발각질제거","손톱","보카스","삼성","쌍둥이칼","헹켈","국산"],"totalShareCount":null,"shareClickCount":null,"socialIncomingCount":0,"meta":{"_tromm":"industry","_app":"harmony"},"totalView":8,"recentView":0,"fbCommentCount":0,"useDefaultOpencomment":"true","viewCoverImage":null,"pcCoverImage":"https://t1.daumcdn.net/liveboard/thevivid/5b7e2c453fa544e0b854c7eff961f1c9.jpg","useLatestOrderComment":"false","cp":null,"viewCoverVideo":null,"summary":[{"title":null,"desc":"<p><b>360도 날이 돌아 가고, 돋보기 달린 손톱깎이 </b></p> \n<p><b>보통 제품 4배 가격, 헹켈 등에 고급 라인으로 수출 </b></p> \n<p><b>날 분리형 발각질제거기도 미국, 일본, 프랑스 등 큰 인기</b> </p> \n<p> </p> \n<p><br></p> \n<p>우리나를 대표하는 제품으로 꼭 반도체 같은 IT제품만 있는 게 아니다. 알고 보면 세계를 주름잡는 의외의 제품들이 있다.&nbsp;<span style=\"color: inherit;\">손톱깎이가 대표적이다.&nbsp;</span></p> \n<p> </p> \n<p><br></p> \n<p>우리나라 손톱깎이의 세계 시장 점유율은 82%나 된다. 전 세계에 돌아다니는 손톱깎이 5개 중 4개가 우리나라 제품이다. 주역 중 한 곳인 보카스(BOCAS)의 천준호 총괄이사를 만났다. 독일의 헹켈(Zwilling Henckels), 스위스의 빅토리눅스(VICTORINOX) 등에 경쟁업체 4배 가격에 손톱깎이를 수출하며 '손톱깎이계의 삼성'이란 평가를 받고 있다. </p> \n<p> </p> \n<p><br></p> \n<p><b>◇첫 제품 개발에만 2년 걸려 </b></p>"},{"title":"","desc":"<p><br></p> \n<p>2004년 설립된 보카스의 첫 제품은 '360도 회전날 손톱깎이'다. 보통의 손톱깎이는 몸이나 손을 이리저리 꼬아 가며 써야 한다. \"원하는 각도로 날을 돌릴 수 있으면 정말 편하겠다는 생각이 드는 거에요. 날만 회전시키면 되니 어렵지 않겠다는 생각이 들더라구요.\" </p> \n<p><br></p> \n<p> </p> \n<p>아이디어 구현은 쉽지 않았다. 손톱깎이를 개발해 출시하는 데 꼬박 2년이 걸렸다. \"기존 생산설비로는 원하는 날을 만들 수 없어 기계설비까지 직접 제작해야 했습니다. 숱한 시행착오 끝에 날을 회전시킬 수 있는 손톱깎이를 개발할 수 있었습니다.\" </p> \n<p><br></p> \n<p> </p> \n<p>제품 개발 후 한국 외에 미국·대만·중국에서도 특허를 취득했다. 360도 날이 돌아가서 몸이 불편한 사람도 남의 도움없이 손톱과 발톱을 깎을 수 있다. “노안인 분들을 위해 손톱깎이 위에 자체 돋보기를 부착한 버전도 있습니다.” 단품과 세트로 구분해 온라인몰 등에 출시했다. </p> \n<p><br></p> \n<p><b> </b></p> \n<p><b>◇손톱깎이를 누가 돈 주고 사니? </b></p>"},{"title":"","desc":"<p><br></p> \n<p>제품만 개발되면 끝날 줄 알았는데, 알고 보니 마케팅이 더 난관이었다. \"주로 우리 기업이 손톱깎이를 만들긴 하는데, 대부분 공장이 중국에 있었어요. 관련 바이어들이 중국만 찾았습니다. 국내에선 바이어 얼굴 보기도 쉽지 않은 거죠. 제품만 좋으면 저절로 팔릴 줄 알았는데, 판로 찾는 일이 그렇게 어려울 줄 몰랐습니다.\" </p> \n<p> </p> \n<p><br></p> \n<p>손톱깎이에 대한 우리나라 사람들의 인식도 장애가 됐다. 손톱깎이는 판촉물로 받는 것이지 돈 주고 사는 게 아니라는 생각이다. 제대로 가격을 책정해서 파는 게 쉽지 않았다. 결국 해외로 방향을 틀기로 했다. </p> \n<p> </p> \n<p><br></p> \n<p>2006년 달랑 샘플만 들고 이탈리아 볼로냐에서 열린 코스모프로프 미용 용품 전시회에 참가했다. 관련 전시회로는 가장 규모가 크다. 기대를 안고 참가했지만 신생 업체에게 눈길을 주는 바이어는 많지 않았다. \"답답하고 속상한 시간이었습니다.\" </p>"}],"title":"매년 25만개씩, 전세계인 쓰는 뜻밖의 한국 제품","version":3,"editor":"hbNJGl5Rtq","updateTime":1611529211488,"regTime":1611396013545,"titleRaw":"매년 25만개씩, 전세계인 쓰는 뜻밖의 한국 제품","img":"https://t1.daumcdn.net/liveboard/thevivid/5b7e2c453fa544e0b854c7eff961f1c9.jpg","path":"thevivid/600bf3ad7f352620e507b15b","isHiddenComment":"false","isDisabledComment":false,"isPublic":true},{"id":"600b9a8e7f352620e507b0b9","channelKey":"trending","serviceKey":"interstella-story","publishKey":"UHBN","consumerId":"1boon","status":"published","description":"","coverImage":"https://t1.daumcdn.net/liveboard/interstella-story/4091f78a34c041a28508e1b43fc1c076.JPG","serviceTemplate":"swipe","publishTime":1611529211423,"tags":["시력","건강","눈보호","시력보호","식품","음식","결명자","알렛츠"],"filteredTags":null,"bizKeywords":["눈보호","결명자","건강","시력","시력보호","음식","식품"],"totalShareCount":null,"shareClickCount":null,"socialIncomingCount":6,"meta":{"_tromm":"food","_app":"harmony"},"totalView":27,"recentView":0,"fbCommentCount":0,"useDefaultOpencomment":"true","viewCoverImage":"https://t1.daumcdn.net/liveboard/interstella-story/4091f78a34c041a28508e1b43fc1c076.JPG","pcCoverImage":"https://t1.daumcdn.net/liveboard/interstella-story/4091f78a34c041a28508e1b43fc1c076.JPG","useLatestOrderComment":"false","cp":null,"viewCoverVideo":null,"summary":[{"title":null,"desc":"<p><b>당근</b></p> \n<p><br></p> \n<p>시력 건강에 도움이 되는 대표적인 음식 당근. 당근은 시력을 보호하고 야맹증을 예방하는 효과가 있다. 당근에는 비타민 A가 풍부한데, 이가 안구 표면의 점막을 건강한 상태로 유지해주고 안구 건조 증상을 예방하여 시력감퇴를 막아준다. 또한 당근에 들어있는 루테인, 리코펜 성분 또한 시력 건강에 기여한다.</p>"},{"title":"","desc":"<p><b>연어</b></p> \n<p><br></p> \n<p>연어 또한 비타민 A 성분이 풍부하게 들어있어 시력 건강에 효과적이다. 뿐만 아니라 연어에 풍부한 오메가-3 지방산은 각종 눈의 질병을 예방하고, 병의 속도를 늦추는데 도움을 준다. 이외에도 연어는 체내 중성지방 수치를 낮추어 주고 노화 방지에도 도움이 되는 등 다양한 효능이 있으니 자주 섭취해주도록 하자.</p>"}],"title":"시력 건강에 도움되는 음식 5","version":3,"editor":"interstella.story","updateTime":1611529211423,"regTime":1611373198124,"titleRaw":"시력 건강에 도움되는 음식 5","img":"https://t1.daumcdn.net/liveboard/interstella-story/4091f78a34c041a28508e1b43fc1c076.JPG","path":"interstella-story/UHBN","isHiddenComment":"false","isDisabledComment":true,"isPublic":true},{"id":"600a70307f352620e507ab68","channelKey":"library","serviceKey":"fortunade","publishKey":"600a70307f352620e507ab68","consumerId":"1boon","status":"published","description":"2002년생도 오늘의 띠별운세 알랴줌!","coverImage":"https://t1.daumcdn.net/liveboard/fortunade/1e0c3bcdd48b4bca90e2dbf3ced66703.png","serviceTemplate":"swipe","publishTime":1611529211314,"tags":["운세","무료운세","오늘의운세","띠별운세","신년운세","월간운세","포춘에이드","사주"],"filteredTags":null,"bizKeywords":["사주","운세","신년운세","띠별운세","무료운세","월간운세","오늘의운세","포춘에이드"],"totalShareCount":null,"shareClickCount":null,"socialIncomingCount":3,"meta":{"_tromm":"fortune","_app":"harmony"},"totalView":7,"recentView":0,"fbCommentCount":0,"useDefaultOpencomment":"true","viewCoverImage":"https://t1.daumcdn.net/liveboard/fortunade/7a1eba7b19e443e4ae812af18b572398.png","pcCoverImage":"","useLatestOrderComment":"false","cp":null,"viewCoverVideo":null,"summary":[],"title":"1월 26일 화요일 띠별운세","version":3,"editor":"z92lYNyYwG","updateTime":1611529211314,"regTime":1611296816686,"titleRaw":"1월 26일 화요일 띠별운세","img":"https://t1.daumcdn.net/liveboard/fortunade/1e0c3bcdd48b4bca90e2dbf3ced66703.png","path":"fortunade/600a70307f352620e507ab68","isHiddenComment":"false","isDisabledComment":false,"isPublic":true},{"id":"6008ed04423bc27f2c9258ea","channelKey":"library","serviceKey":"appstory","publishKey":"210122_1","consumerId":"1boon","status":"published","description":"헤어드라이기 추천","coverImage":"https://t1.daumcdn.net/liveboard/appstory/d787da161c294548bd40d82507c46df3.JPG","serviceTemplate":"listicle","publishTime":1611529211207,"tags":["헤어드라이기","헤어","드라이기","헤어드라이어","드라이어","파테크하이퍼소닉드라이기BLDCG1","파테크소닉접이식드라이기","JMW터보프리미어드라이기MS6210A","JMW에어컬렌션드라이기MS800","JMW터치온드라이기MCS600"],"filteredTags":null,"bizKeywords":["드라이어","드라이기","헤어드라이어","헤어","헤어드라이기","파테크하이퍼소닉드라이기BLDCG1","파테크소닉접이식드라이기"],"totalShareCount":null,"shareClickCount":null,"socialIncomingCount":0,"meta":{"_app":"harmony","_tromm":"device","_approvedAt":"1611529218841","_isApproved":"true"},"totalView":49,"recentView":0,"fbCommentCount":0,"useDefaultOpencomment":"true","viewCoverImage":"https://t1.daumcdn.net/liveboard/appstory/1af93228890746c097f7676e6a69ef4e.jpg","pcCoverImage":"https://t1.daumcdn.net/liveboard/appstory/d787da161c294548bd40d82507c46df3.JPG","useLatestOrderComment":"false","cp":null,"viewCoverVideo":null,"summary":[{"title":"","desc":"<p style=\"text-align: justify; \">샤워 후 머리를 말릴 때 헤어드라이어는 필수다. 옛날에는 드라이어가 여성의 전유물처럼 여겨졌지만, 지금은 남녀노소를 불문하고 모두에게 필요한 생활 필수 가전으로 자리 잡았다. 헤어드라이어 없이도 머리를 말릴 수 있지만, 드라이어의 도움을 받는다면 훨씬 빠르게 모발을 건조시킬 수 있다. 드라이어는 단순히 젖은 머리를 말리는 용도뿐만 아니라 헤어 스타일링에도 반드시 필요하다. 시중에 다양한 제품들이 출시되어 있는데, 드라이어를 고를 때에도 고민이 필요하다. 과연 어떤 제품이 어떤 기능을 가지고 있고, 또 어떤 용도로 선택하면 좋을까?</p>"},{"title":"JMW 에어컬렉션 드라이어\n<br>","desc":""}],"title":"전문 미용사도 추천하는 헤어드라이기","version":2,"editor":"QVjvYlLoSD","updateTime":1611529211207,"regTime":1611197700510,"titleRaw":"전문 미용사도 추천하는 헤어드라이기","img":"https://t1.daumcdn.net/liveboard/appstory/d787da161c294548bd40d82507c46df3.JPG","path":"appstory/210122_1","isHiddenComment":"false","isDisabledComment":false,"isPublic":true},{"id":"6008ccde7f352620e5079b84","channelKey":"trending","serviceKey":"faibet","publishKey":"uggfashion","consumerId":"1boon","status":"published","description":"By. 파이베트 구민승기자, 김미영 칼럼니스트","coverImage":"https://t1.daumcdn.net/liveboard/faibet/e928ccd3f1e544e89964629caccc3766.JPG","serviceTemplate":"listicle","publishTime":1611529211144,"tags":["파이베트","파이스타일","어그부츠","어그패션","겨울철신발","신발패션"],"filteredTags":null,"bizKeywords":["어그부츠","겨울철신발","신발패션","어그패션","파이베트"],"totalShareCount":null,"shareClickCount":null,"socialIncomingCount":0,"meta":{"_tromm":"fashion","_app":"harmony","_approvedAt":"1611529217689","_isApproved":"true"},"totalView":41,"recentView":0,"fbCommentCount":0,"useDefaultOpencomment":"true","viewCoverImage":null,"pcCoverImage":"","useLatestOrderComment":"false","cp":null,"viewCoverVideo":null,"summary":[{"title":"","desc":"<p style=\"text-align: center;\">안녕하세요. 오늘은 이번 FW에</p> \n<p style=\"text-align: center;\">자주 보이는 아이템 </p> \n<p style=\"text-align: center;\">어그부츠, 호보백 등</p> \n<p style=\"text-align: center;\">다양한 스타일을 보여드리려고 해요!</p>"},{"title":"","desc":"<div style=\"text-align: center\"> \n <img src=\"https://t1.daumcdn.net/liveboard/emoticon/kakaofriends/v1/niniz2/12.gif\" alt=\"아하\" class=\"sa-emoticon\"> \n</div>"},{"title":null,"desc":"<p style=\"text-align: center;\">겨울철 가방과 신발 코디에 대해서</p> \n<p style=\"text-align: center;\">어려움을 겪고 계셨던 분이라면</p> \n<p style=\"text-align: center;\">제가 알려드리는 코디를 참고해봐주세요!</p>"}],"title":"어그부츠, 호보백 핫한 아이템은 다! 입어보자","version":2,"editor":"wYvC95yZ5I","updateTime":1611529211144,"regTime":1611189470971,"titleRaw":"어그부츠, 호보백 핫한 아이템은 다! 입어보자","img":"https://t1.daumcdn.net/liveboard/faibet/e928ccd3f1e544e89964629caccc3766.JPG","path":"faibet/uggfashion","isHiddenComment":"false","isDisabledComment":true,"isPublic":true},{"id":"6007c3c18c31e10ed1c8639a","channelKey":"animal","serviceKey":"koreadognews","publishKey":"6007c3c18c31e10ed1c8639a","consumerId":"1boon","status":"published","description":"","coverImage":"https://t1.daumcdn.net/liveboard/koreadognews/00eaecee2c41422f91c3c01a3c033aff.png","serviceTemplate":"swipe","publishTime":1611529210946,"tags":["동물","반려동물","반려묘","고양이","귀여운 고양이","고양이 키우기","우유"],"filteredTags":null,"bizKeywords":["반려동물","고양이","고양이키우기","우유","반려묘","귀여운고양이","동물"],"totalShareCount":null,"shareClickCount":null,"socialIncomingCount":1,"meta":{"_tromm":"animal","_app":"harmony"},"totalView":16,"recentView":0,"fbCommentCount":0,"useDefaultOpencomment":"true","viewCoverImage":"https://t1.daumcdn.net/liveboard/koreadognews/9727fb11ffdf4b89a58d55a6dc93b9c3.png","pcCoverImage":"https://t1.daumcdn.net/liveboard/koreadognews/18cdfd35d3b6435eae58a5751b2a8f1f.png","useLatestOrderComment":"false","cp":null,"viewCoverVideo":null,"summary":[{"title":null,"desc":"<p style=\"text-align: center;\">한 고양이가<b> 목이 긴 컵 </b>안에 들어 있는<b> 우유</b>를 마시고 싶었나 봅니다.</p> \n<p style=\"text-align: center;\"><br></p> \n<p style=\"text-align: center;\">하지만<b> 컵이 너무 길어</b> <b>어떻게 마실까</b> 궁금했습니다.</p>"}],"title":"컵에 담긴 우유가 먹고 싶던 고양이가 한 방법은?!","version":2,"editor":"gU4LCcyXbX","updateTime":1611529210946,"regTime":1611121600940,"titleRaw":"컵에 담긴 우유가 먹고 싶던 고양이가 한 방법은?!","img":"https://t1.daumcdn.net/liveboard/koreadognews/00eaecee2c41422f91c3c01a3c033aff.png","path":"koreadognews/6007c3c18c31e10ed1c8639a","isHiddenComment":"false","isDisabledComment":false,"isPublic":true},{"id":"6007ba088c31e10ed1c86302","channelKey":"library","serviceKey":"dailylife","publishKey":"210122_1","consumerId":"1boon","status":"published","description":"저장해두면 10년 든든한 10가지 선물 리스트","coverImage":"https://t1.daumcdn.net/liveboard/dailylife/b1577bab187947cfb794314a2d68486f.JPG","serviceTemplate":"listicle","publishTime":1611529210214,"tags":["선물추천","선물","추천","부모님선물","부모님선물추천","결혼기념일선물추천","부모님결혼기념일선물","부모님결혼기념일선물추천","결혼기념일추천선물","용돈케이크"],"filteredTags":null,"bizKeywords":["부모님선물","부모님선물추천","선물추천","선물","부모님결혼기념일선물","결혼기념일선물추천","결혼기념일추천선물","부모님결혼기념일선물추천","용돈케이크","추천"],"totalShareCount":null,"shareClickCount":null,"socialIncomingCount":0,"meta":{"_app":"harmony","_tromm":"family_relation","_approvedAt":"1611529216055","_isApproved":"true"},"totalView":35,"recentView":0,"fbCommentCount":0,"useDefaultOpencomment":"true","viewCoverImage":"https://t1.daumcdn.net/liveboard/dailylife/8648cc36aff7471381f9ba25160d12f7.jpg","pcCoverImage":"https://t1.daumcdn.net/liveboard/dailylife/b1577bab187947cfb794314a2d68486f.JPG","useLatestOrderComment":"false","cp":null,"viewCoverVideo":null,"summary":[{"title":"","desc":"<p style=\"text-align: justify; \">생신만큼이나 신경 쓰이는 부모님의 결혼기념일, 두 분 다 만족시켜 드릴 만한 선물을 고르는 것이 여간 어려운 일이 아니다. 두 분 모두 건강하게 함께하실 때 좋은 추억을 하나라도 더 만들어드리고 싶지만, 막상 기념일이 다가올수록 무엇을 해드려야 할지 막막해지는 것이 현실이다. 남들은 과연 부모님 결혼기념일에 어떤 선물을 할까? 만족도가 높기로 유명한 10가지 결혼기념일 추천 선물을 준비했다. 저장해둔다면 10년 동안 든든할 수 있을 것이다. </p>"},{"title":"맞춤 케이크\n<br>","desc":""}],"title":"매년 '극한' 고민되는 부모님 결혼 기념일 선물, 뭐가 좋을까?","version":2,"editor":"QVjvYlLoSD","updateTime":1611529210214,"regTime":1611119112228,"titleRaw":"매년 '극한' 고민되는 부모님 결혼 기념일 선물, 뭐가 좋을까?","img":"https://t1.daumcdn.net/liveboard/dailylife/b1577bab187947cfb794314a2d68486f.JPG","path":"dailylife/210122_1","isHiddenComment":"false","isDisabledComment":false,"isPublic":true},{"id":"6000533727d2074a598e8098","channelKey":"trending","serviceKey":"shortoon","publishKey":"campus066","consumerId":"1boon","status":"published","description":"by. 우리","coverImage":"https://t1.daumcdn.net/liveboard/shortoon/e715ded496484835b49a049663115c42.jpeg","serviceTemplate":"swipe","publishTime":1611529210142,"tags":[],"filteredTags":null,"bizKeywords":null,"totalShareCount":null,"shareClickCount":null,"socialIncomingCount":8,"meta":{"_tromm":"humor","_app":"harmony","_approvedAt":"1611529214698","_isApproved":"true"},"totalView":14,"recentView":0,"fbCommentCount":0,"useDefaultOpencomment":"true","viewCoverImage":null,"pcCoverImage":"","useLatestOrderComment":"false","cp":null,"viewCoverVideo":null,"summary":[{"title":"","desc":"<p style=\"text-align: center; \">더 많은 짧툰은?</p> \n<p style=\"text-align: center; \"><br></p> \n<p style=\"text-align: center; \">&gt;<a href=\"https://1boon.kakao.com/shortoon\">https://1boon.kakao.com/shortoon</a></p>"}],"title":"생일을 맞이하는 유형","version":5,"editor":"shortoon","updateTime":1611529210142,"regTime":1610634039466,"titleRaw":"생일을 맞이하는 유형","img":"https://t1.daumcdn.net/liveboard/shortoon/e715ded496484835b49a049663115c42.jpeg","path":"shortoon/campus066","isHiddenComment":"false","isDisabledComment":false,"isPublic":true},{"id":"600df9d17f352620e507b30a","channelKey":"library","serviceKey":"bizion","publishKey":"600df9d17f352620e507b30a","consumerId":"1boon","status":"published","description":"프랑스 기반의 신생기업 'Nymphea Labs'가 만든 'Solar Scare'","coverImage":"https://t1.daumcdn.net/liveboard/bizion/5eafdcc46aab449eaca52c8e43446e7d.png","serviceTemplate":"listicle","publishTime":1611528675016,"tags":["Nymphea","SolarScare","mosquito","님피아","솔라스케어","모기","말라리아","유충","우물","바이러스"],"filteredTags":null,"bizKeywords":["바이러스","모기","말라리아","유충","우물","mosquito","님피아"],"totalShareCount":null,"shareClickCount":null,"socialIncomingCount":0,"meta":{"_tromm":"industry","_app":"harmony"},"totalView":1,"recentView":0,"fbCommentCount":0,"useDefaultOpencomment":"true","viewCoverImage":null,"pcCoverImage":"","useLatestOrderComment":"false","cp":null,"viewCoverVideo":null,"summary":[{"title":"각종 질병을 퍼뜨리는 가장 위험한 해충 '모기'","desc":""},{"title":"","desc":"<p>세계보건기구(WHO)의 2019년 자료에 따르면 한 해 41만 명에 달하는 사람들이 말라리아로 사망했다. 특히 어린이가 말라리에 가장 취약한데 이들을 살릴 수 있는 가장 근원적인 방법은 바로 모기에 물리지 않는 것이다. </p>\n<p><br></p> \n<p> </p> \n<p>우리는 모기의 위험성을 종종 언급해왔다. 모기는 말라리아 뿐 아니라 지카, 뎅기열, 나일, 치쿤구니아 바이러스와 같은 위험한 질병을 퍼뜨리는 매우 위험한 해충으로 잘 알려져 있다.&nbsp;</p>"},{"title":"","desc":"<p>시중에서 구입할 수 있는 제품들은 대부분이 모기에 물리지 않도록 도와주는 것들 뿐이다. 그러나 프랑스 기반의 신생기업 '님피아 랩스(Nymphea Labs)'는 모기의 번식과 확산을 차단하는 새로운 솔루션을 개발했다. </p>\n<p><br></p> \n<p> </p> \n<p>님피아가 주목한 것은 바로 모기 자체가 아닌 모기가 번식하기 위해 유충을 낳는 장소 즉 '고인 우물'이다. 모기 유충이 잘 자라기 위해서는 흐르지 않고 고여 있는 물이 필요하다. 바로 이곳에서 모기 유충을 죽이는 것이 님피아가 생각한 아이디어이다.&nbsp;&nbsp;</p>"}],"title":"모기의 번식을 막는 신통방통한 기기","version":2,"editor":"xMyvpCIqHM","updateTime":1611528675016,"regTime":1611528657477,"titleRaw":"모기의 번식을 막는 신통방통한 기기","img":"https://t1.daumcdn.net/liveboard/bizion/5eafdcc46aab449eaca52c8e43446e7d.png","path":"bizion/600df9d17f352620e507b30a","isHiddenComment":"false","isDisabledComment":false,"isPublic":true},{"id":"600a525b7f352620e507a941","channelKey":"trending","serviceKey":"sharehows_1boon","publishKey":"Year-endsettlement","consumerId":"1boon","status":"published","description":"자산관리의 시작, 연말정산의 개념부터 방법까지 정리해봤다.","coverImage":"https://t1.daumcdn.net/liveboard/sharehows_1boon/18cc526af4334fb29defd05ad14302c2.JPG","serviceTemplate":"videoview","publishTime":1611527409256,"tags":["자산관리","자산관리방법","재테크","연말정산","연말정산방법","소득공제","연말정산법"],"filteredTags":null,"bizKeywords":["재테크","자산관리","소득공제","연말정산","자산관리방법","연말정산방법","연말정산법"],"totalShareCount":null,"shareClickCount":null,"socialIncomingCount":203,"meta":{"_tromm":"home_life","_app":"harmony","_approvedAt":"1611527415180","_isApproved":"true"},"totalView":254,"recentView":0,"fbCommentCount":0,"useDefaultOpencomment":"true","viewCoverImage":null,"pcCoverImage":"","useLatestOrderComment":"false","cp":null,"viewCoverVideo":"http://www.youtube.com/embed/X_AUl2H_a1U","summary":[{"title":null,"desc":"<p>연말정산은 직장생활을 오래 한 이들도 늘 어려워한다 경력직뿐만 아니라 사회초년생이라면 더더욱 지금부터 개념을 잘 잡아두고, 준비를 철저히해보면 어떨까? 자산관리의 시작, 연말정산의 개념부터 방법까지 정리해봤다.</p>"},{"title":"","desc":"<p>연말정산은 일단 우리가 세금을 내는 것에서부터 출발한다. 대표적으로 근로소득세가 있다. 연말정산은 이러한 근로소득자가 냈던 근로 소득세를 연말에 돌려받는 과정을 말한다.</p>"}],"title":"자산관리 초보를 위한 연말정산 개념과 방법","version":2,"editor":"OxOUtNXQ3u","updateTime":1611527409256,"regTime":1611289177482,"titleRaw":"자산관리 초보를 위한 연말정산 개념과 방법","img":"https://t1.daumcdn.net/liveboard/sharehows_1boon/18cc526af4334fb29defd05ad14302c2.JPG","path":"sharehows_1boon/Year-endsettlement","isHiddenComment":"false","isDisabledComment":false,"isPublic":true},{"id":"600d5c758c31e10ed1c881a6","channelKey":"library","serviceKey":"ziksir","publishKey":"600d5c758c31e10ed1c881a6","consumerId":"1boon","status":"published","description":"그는 가족에 의해 2m 두께의 콘크리트 아래 잠들었다.","coverImage":"https://t1.daumcdn.net/liveboard/ziksir/eb1a71caab9b4a56a520f22e336dd35d.jpg","serviceTemplate":"listicle","publishTime":1611526215158,"tags":["찰리","시신","오닐","가족","대상"],"filteredTags":null,"bizKeywords":["대상","오닐","찰리","가족"],"totalShareCount":null,"shareClickCount":null,"socialIncomingCount":1,"meta":{"_tromm":"healing","_app":"harmony"},"totalView":10,"recentView":0,"fbCommentCount":0,"useDefaultOpencomment":"true","viewCoverImage":null,"pcCoverImage":"https://t1.daumcdn.net/liveboard/ziksir/eb1a71caab9b4a56a520f22e336dd35d.jpg","useLatestOrderComment":"false","cp":null,"viewCoverVideo":null,"summary":[{"title":"","desc":"<p>유명인 숭배 신드롬(Celebrity Worship Syndrom)이라는 용어가 있다. 이는 스포츠 스타, 연예인 등 유명인에게 과도하게 집착하는 것을 말한다. 유명인 숭배 신드롬을 보이는 사람은 정상적인 생활이 불가할 정도로 숭배 대상에 빠져들거나, 숭배 대상이 쓴 물건 수집에 집착하기도 하고 납치 등 범죄를 저지르기도 한다. 2009년 故 최진실 유골을 훔쳐 세상을 떠들썩하게 했던 범인도 ‘최진실이 꿈속에 나타나 무덤을 옮겨달라’고 진술하는 등 전형적인 ‘유명인 숭배 신드롬’ 증상을 보였다. </p> \n<p> </p> \n<p> </p> \n<p> </p> \n<p><br></p> \n<p>‘록의 황제’ 엘비스 프레슬리도 이 수난을 피해가지 못했다. 엘비스 프레슬리가 사망한 직후인 1977년, ‘내셔널 인쾨이어러’라는 주간 대중잡지에 충격적인 제보가 들어왔다. 엘비스의 친척 중 한 명이 그의 시신을 몰래 찍어 들고 온 것이다. ‘내셔널 인콰이어러’는 엘비스 프레슬리의 시신 사진을 1만 8천 달러에 사들여 1면 톱으로 실었고, 그 잡지의 판매부수는 잡지 발행 역사상 최고를 기록했다.</p>"},{"title":"","desc":"<p>20세기를 대표했던 영화배우 찰리 채플린(Charles Chaplin, 1889~1977, 영국) 역시 ‘유명인 숭배 신드롬’의 피해자였다. 채플린은 엘비스 프레슬리와 같은 해인 1977년에 사망하여, 스위스의 코시어 서베이 공동묘지에 묻혔다. 그러나 4개월 후인 1978년 3월1일, 그의 무덤이 파헤쳐지고 시신이 도굴되는 사건이 발생했다. 11주만에 제네바 호수 근처에서 시신이 발견되었고, 범인도 체포되며 사건은 일단락되었다. 그러나 유족과 전 세계의 채플린 팬들이 받은 충격은 가시지 않았다. </p> \n<p> </p> \n<p><br></p> \n<p> </p> \n<p> </p> \n<p>특히 채플린의 아내인 우나 오닐이 받은 상처는 컸다. 두 사람은 숱한 어려움을 딛고 맺어진 부부였던 탓이다. 노벨상 작가인 유진 오닐의 딸이었던 그녀는 채플린의 네 번째 아내이자 마지막 아내였다. </p> \n<p> </p> \n<p> </p> \n<p><br></p> \n<p> </p> \n<p>18살의 나이 차이를 뛰어넘은 그들의 스캔들은 당시 세상을 떠들썩하게 만들었다. 특히 아버지인 유진 오닐은 딸 우나가 자신보다 한 살 어린 찰리 채플린과 결혼하는 것을 극구 반대했다. 하지만 그녀는 그럼에도 불구하고 찰리 채플린과의 결혼을 강행했다. </p> \n<p> </p> \n<p><br></p> \n<p> </p> \n<p> </p> \n<p>찰리 채플린과 우나 오닐은 35년간 함께 살았고, 8명의 자녀를 두었다. 그들은 1953년 스위스에 정착했으며 1977년 크리스마스 이브 찰리 채플린이 88세의 나이로 죽을 때까지 함께 해왔다. </p> \n<p> </p> \n<p><br></p>"}],"title":"찰리 채플린의 관 위로 콘크리트가 부어진 까닭은?","version":2,"editor":"RIxR0TXdx1","updateTime":1611526215158,"regTime":1611488373335,"titleRaw":"찰리 채플린의 관 위로 콘크리트가 부어진 까닭은?","img":"https://t1.daumcdn.net/liveboard/ziksir/eb1a71caab9b4a56a520f22e336dd35d.jpg","path":"ziksir/600d5c758c31e10ed1c881a6","isHiddenComment":"false","isDisabledComment":false,"isPublic":true},{"id":"600be08d7f352620e507b133","channelKey":"issue","serviceKey":"lawnlife","publishKey":"600be08d7f352620e507b133","consumerId":"1boon","status":"published","description":"","coverImage":"https://t1.daumcdn.net/liveboard/lawnlife/6d98929ca4bb4fed9559e1e7b092a024.JPG","serviceTemplate":"swipe","publishTime":1611526215034,"tags":["반려견","반려견오진","반려견치료","반려견소송","애완견","댕댕이"],"filteredTags":null,"bizKeywords":["애완견","반려견","댕댕이"],"totalShareCount":null,"shareClickCount":null,"socialIncomingCount":21,"meta":{"_tromm":"animal","_app":"harmony"},"totalView":60,"recentView":0,"fbCommentCount":0,"useDefaultOpencomment":"true","viewCoverImage":"https://t1.daumcdn.net/liveboard/lawnlife/6d98929ca4bb4fed9559e1e7b092a024.JPG","pcCoverImage":"","useLatestOrderComment":"false","cp":null,"viewCoverVideo":null,"summary":[],"title":"'수의사 오진 사망' 반려견 치료비 배상 받을 수 있나요?","version":2,"editor":"9MjLsCQarN","updateTime":1611526215034,"regTime":1611391117228,"titleRaw":"'수의사 오진 사망' 반려견 치료비 배상 받을 수 있나요?","img":"https://t1.daumcdn.net/liveboard/lawnlife/6d98929ca4bb4fed9559e1e7b092a024.JPG","path":"lawnlife/600be08d7f352620e507b133","isHiddenComment":"false","isDisabledComment":false,"isPublic":true},{"id":"6007dea57f352620e5079755","channelKey":"trending","serviceKey":"mbcevery1","publishKey":"6007dea57f352620e5079755","consumerId":"1boon","status":"published","description":"전액 기부!! 진짜 대단합니다","coverImage":"https://t1.daumcdn.net/liveboard/mbcevery1/f4f502c41f5b44748efaca5af3067532.jpeg","serviceTemplate":"listicle","publishTime":1611526214123,"tags":["영지","놀면뭐하니"],"filteredTags":null,"bizKeywords":["영지","놀면뭐하니"],"totalShareCount":null,"shareClickCount":null,"socialIncomingCount":11,"meta":{"_tromm":"enter_general","_app":"harmony"},"totalView":146,"recentView":0,"fbCommentCount":0,"useDefaultOpencomment":"true","viewCoverImage":null,"pcCoverImage":"https://t1.daumcdn.net/liveboard/mbcevery1/9056376212c946b29e85ca227f849206.jpeg","useLatestOrderComment":"false","cp":null,"viewCoverVideo":null,"summary":[{"title":"","desc":"<p style=\"text-align: center;\">'놀면 뭐하니?'에 예능유망주로</p> \n<p style=\"text-align: center;\">출연한 래퍼 이영지!</p>"}],"title":"하루만에 매출 1억 찍은 20살 여자래퍼","version":2,"editor":"RcJcu3D7dD","updateTime":1611526214123,"regTime":1611128485684,"titleRaw":"하루만에 매출 1억 찍은 20살 여자래퍼","img":"https://t1.daumcdn.net/liveboard/mbcevery1/f4f502c41f5b44748efaca5af3067532.jpeg","path":"mbcevery1/6007dea57f352620e5079755","isHiddenComment":"false","isDisabledComment":false,"isPublic":true},{"id":"600d6661423bc27f2c926d47","channelKey":"library","serviceKey":"solutionmaker16","publishKey":"gangyeonnam301","consumerId":"1boon","status":"published","description":"장성규 이야기","coverImage":"https://t1.daumcdn.net/liveboard/solutionmaker16/bc97c0f735b1475498d5c79d1c8b881d.gif","serviceTemplate":"swipe","publishTime":1611525608015,"tags":["강연읽어주는남자","자기계발","동기부여"],"filteredTags":null,"bizKeywords":["자기계발","동기부여"],"totalShareCount":null,"shareClickCount":null,"socialIncomingCount":1,"meta":{"_tromm":"learning","_app":"harmony"},"totalView":8,"recentView":0,"fbCommentCount":0,"useDefaultOpencomment":"true","viewCoverImage":"https://t1.daumcdn.net/liveboard/solutionmaker16/d2295aa09dab4e63a5bf9da73f38b70b.JPG","pcCoverImage":"https://t1.daumcdn.net/liveboard/solutionmaker16/254e969d3e344fe6bab11bd32470b64d.JPG","useLatestOrderComment":"false","cp":null,"viewCoverVideo":null,"summary":[],"title":"요즘 가장 잘나가는 아나운서 출신 연예인","version":4,"editor":"GeQLmXqvLL","updateTime":1611525608015,"regTime":1611490913565,"titleRaw":"요즘 가장 잘나가는 아나운서 출신 연예인","img":"https://t1.daumcdn.net/liveboard/solutionmaker16/bc97c0f735b1475498d5c79d1c8b881d.gif","path":"solutionmaker16/gangyeonnam301","isHiddenComment":"false","isDisabledComment":false,"isPublic":true},{"id":"600a9df88c31e10ed1c87de1","channelKey":"trending","serviceKey":"COMPANYTIMES","publishKey":"jobplanet99","consumerId":"1boon","status":"published","description":"코로나19로 ‘연봉 삭감’…\"근로자 동의 필요해\"","coverImage":"https://t1.daumcdn.net/liveboard/COMPANYTIMES/9bbda553fe5c408cadbd0ac9e264bdfa.jpg","serviceTemplate":"listicle","publishTime":1611525607812,"tags":["잡플래닛","데이터J","직장인","회사생활","직장생활","혼돈의 직장생활"],"filteredTags":null,"bizKeywords":["직장인","직장생활","잡플래닛","회사생활","혼돈의직장생활"],"totalShareCount":null,"shareClickCount":null,"socialIncomingCount":0,"meta":{"_tromm":"employ","_app":"harmony"},"totalView":10,"recentView":0,"fbCommentCount":0,"useDefaultOpencomment":"true","viewCoverImage":null,"pcCoverImage":"","useLatestOrderComment":"false","cp":null,"viewCoverVideo":null,"summary":[{"title":"","desc":"<p>연봉 협상의 계절이 왔습니다. 연봉 협상이 아니라 '연봉 통보'라며 한숨 짓는 분들도 있을 테고, 어떻게 하면 직장에서 자신의 가치를 더 높일 수 있을지 고민하고 있는 분들도 있을 텐데요. 그런데 위의 사례처럼 연봉 협상을 진행하지 않는 기업도 심심치 않게 보입니다. 연봉 협상을 안 하더라도 법적인 문제는 없는 걸까요?</p>"},{"title":"◇ 연봉 협상은 매년 필수? \"법적으로 정해진 바 없어\"","desc":""},{"title":"","desc":"<p>연봉 협상을 이해하기 위해서는 먼저 <b>연봉제</b>라는 급여 제도를 살펴봐야 합니다. 연봉제는 월 급여와 고정식 수당 및 성과급을 포함하여 근로자의 업무 성과에 따라 <b>임금을 1년 단위로 계약하는 제도</b>입니다. 연봉을 매달 '월 급여'로 지급하는 건, 근로기준법상의 '임금 지급 원칙' 중 '매달 1회 지급일을 지정해서 지급해야 한다'는 조항 때문이죠. 월 단위의 급여와 고정 수당을 포함해 계약하는 월급제나, 근속연수나 연령에 따라 일정 금액을 호봉으로 책정해 임금을 지급하는 호봉제와는 차이를 보입니다.</p>"}],"title":"\"연봉 협상은 꼭 매년 해야 하나요?\"","version":2,"editor":"Vh5qw2TPjO","updateTime":1611525607812,"regTime":1611308536509,"titleRaw":"\"연봉 협상은 꼭 매년 해야 하나요?\"","img":"https://t1.daumcdn.net/liveboard/COMPANYTIMES/9bbda553fe5c408cadbd0ac9e264bdfa.jpg","path":"COMPANYTIMES/jobplanet99","isHiddenComment":"false","isDisabledComment":false,"isPublic":true},{"id":"600a49e17f352620e507a8cf","channelKey":"library","serviceKey":"macarong","publishKey":"600a49e17f352620e507a8cf","consumerId":"1boon","status":"published","description":"","coverImage":"https://t1.daumcdn.net/liveboard/macarong/8701c27ab69a4757a80e64842b32170e.png","serviceTemplate":"listicle","publishTime":1611525607646,"tags":["자동차버튼기능교과서","자동차책","운전면허","초보운전","자동차상식","상향등","하향등","안개등"],"filteredTags":null,"bizKeywords":["운전면허","초보운전","자동차책","안개등","자동차상식","상향등","하향등","자동차버튼기능교과서"],"totalShareCount":null,"shareClickCount":null,"socialIncomingCount":0,"meta":{"_tromm":"car","_app":"harmony"},"totalView":10,"recentView":0,"fbCommentCount":0,"useDefaultOpencomment":"true","viewCoverImage":null,"pcCoverImage":"","useLatestOrderComment":"false","cp":null,"viewCoverVideo":null,"summary":[{"title":null,"desc":"<p>가로등도 없는 어두컴컴한 길, 자동차 전조등을 비롯한 각종 라이트는 운전자에게 없어서는 안 될 눈과 같은 존재입니다.</p> \n<p><br></p> \n<p>하지만 라이트를 올바르게 사용하지 못하면, 나는 물론 다른 운전자의 운전을 방해하여 심하면 사고를 유발할 수도 있는데요.</p> \n<p><br></p> \n<p>차량관리 앱 마이클과 함께 <b>잘못 사용하는 자동차 라이트 3가지를 알아보고, 올바른 사용 방법을 확인해볼까요?</b></p>"},{"title":"1. 마주 오는 차의 시야를 차단, 상향등","desc":""},{"title":"","desc":"<p>자동차의 전조등은 크게 <b>상향등</b>과 <b>하향등</b>으로 나누어집니다.</p>"}],"title":"중요한데 잘못 사용하는 자동차 라이트 TOP3","version":2,"editor":"uH7mNvu81G","updateTime":1611525607646,"regTime":1611287009377,"titleRaw":"중요한데 잘못 사용하는 자동차 라이트 TOP3","img":"https://t1.daumcdn.net/liveboard/macarong/8701c27ab69a4757a80e64842b32170e.png","path":"macarong/600a49e17f352620e507a8cf","isHiddenComment":"false","isDisabledComment":false,"isPublic":true}],"pagingInfo":{"currentPageIndex":1,"totalPageCount":14435,"totalRecordCount":288683,"pageSize":20,"hasPrev":false,"hasNext":true}}