{"status":{"code":200,"name":"OK"},"data":[{"id":"608a592c4d31cb16eb995a94","channelKey":"enter","serviceKey":"feelthemovie","publishKey":"608a592c4d31cb16eb995a94","consumerId":"1boon","status":"published","description":"<미션 임파서블 7> 기차 촬영중 추락중인 카매라맨을 구한 톰 크루즈","coverImage":"https://t1.daumcdn.net/liveboard/feelthemovie/671c9ad19d4748f4a6ef108a65f5dae1.JPG","serviceTemplate":"listicle","publishTime":1619679537529,"tags":["톰크루즈","미션임파서블7","미션임파서블8","영화비하인드","영화뉴스","필더무비"],"filteredTags":null,"bizKeywords":null,"totalShareCount":null,"shareClickCount":null,"socialIncomingCount":0,"meta":{"_tromm":"movie","_app":"harmony"},"totalView":1,"recentView":0,"fbCommentCount":0,"useDefaultOpencomment":"true","viewCoverImage":null,"pcCoverImage":"https://t1.daumcdn.net/liveboard/feelthemovie/671c9ad19d4748f4a6ef108a65f5dae1.JPG","useLatestOrderComment":"false","cp":null,"viewCoverVideo":null,"summary":[{"title":"곧 환갑인데… 맨손으로 기차에 매달린 월드 스타 근황","desc":"<미션 임파서블> 7, 8편에 또 고난도 액션 연기 선보이는 톰 크루즈 근황"},{"title":"*바로 잡습니다!","desc":""},{"title":"","desc":"<div style=\"text-align: center\"> \n <img src=\"https://t1.daumcdn.net/liveboard/emoticon/kakaofriends/v4/theme/theme_apeach_jayg.gif\" alt=\"혼나는 제이지\" class=\"sa-emoticon\"> \n</div>"}],"version":2,"title":"기차에 추락하는 스태프를 구조한 월드스타의 모습","editor":"Kpou0mcYXV","updateTime":1619679537529,"regTime":1619679532074,"titleRaw":"기차에 추락하는 스태프를 구조한 월드스타의 모습","img":"https://t1.daumcdn.net/liveboard/feelthemovie/671c9ad19d4748f4a6ef108a65f5dae1.JPG","path":"feelthemovie/608a592c4d31cb16eb995a94","isHiddenComment":"false","isDisabledComment":false,"isPublic":true},{"id":"608a58a818c79f2de6013012","channelKey":"library","serviceKey":"ppss","publishKey":"608a58a818c79f2de6013012","consumerId":"1boon","status":"published","description":"\"소비보다도 고객시간을 빼앗아라!\"","coverImage":"https://t1.daumcdn.net/liveboard/ppss/468be2f4232a420a98cbf547134fe676.jpg","serviceTemplate":"listicle","publishTime":1619679452514,"tags":["이마트","체류시간","대형마트","야구장","정용진","신세계","ㅍㅍㅅㅅ","글쓰는워커비"],"filteredTags":null,"bizKeywords":null,"totalShareCount":null,"shareClickCount":null,"socialIncomingCount":null,"meta":{"_tromm":"industry","_app":"harmony"},"totalView":1,"recentView":0,"fbCommentCount":0,"useDefaultOpencomment":"true","viewCoverImage":null,"pcCoverImage":"","useLatestOrderComment":"false","cp":null,"viewCoverVideo":null,"summary":[{"title":null,"desc":"<p>정용진 부회장이 2014년 내놓은 말이다. 더이상 대형마트는 싸고 좋은 품질만으로 승부를 볼 수 없다고 판단했다. 이마트의 경쟁자는 건너편 롯데마트가 아니라, 놀이공원과 야구장이라고 직접 말하기도 했다. </p> \n<p><br></p> \n<p>무슨 말이냐면, 전통적인 대형마트의 형태로는 성장에 한계가 있다는 것이다. 더 큰 성장을 위해서는 대형마트로 장 보러 오는 사람뿐만 아니라, 그외의 영역에서도 고객을 유치해야 한다는 판단이었다.</p> \n<p><br></p> \n<p> </p>"},{"title":"1. 전통적인 대형마트에서 신경 쓰지 못한 대상은?","desc":""}],"version":3,"title":"정용진이 야구단을 인수한 이유는 바로 \"이것\" 때문이다","editor":"ppss","updateTime":1619679452514,"regTime":1619679400664,"titleRaw":"정용진이 야구단을 인수한 이유는 바로 \"이것\" 때문이다","img":"https://t1.daumcdn.net/liveboard/ppss/468be2f4232a420a98cbf547134fe676.jpg","path":"ppss/608a58a818c79f2de6013012","isHiddenComment":"false","isDisabledComment":false,"isPublic":true},{"id":"60890ad618c79f2de6012668","channelKey":"enter","serviceKey":"newsade","publishKey":"makeupfix","consumerId":"1boon","status":"published","description":"처음 한 것처럼, 뭉친 화장 되살리는 법","coverImage":"https://t1.daumcdn.net/liveboard/newsade/cc736899902e4246ad13c40f23d3f094.PNG","serviceTemplate":"listicle","publishTime":1619679013959,"tags":["수정화장","하니","여자친구","연예인메이크업","수진","전혜빈","메이크업팁","수정메이크업","뉴스에이드"],"filteredTags":null,"bizKeywords":null,"totalShareCount":null,"shareClickCount":null,"socialIncomingCount":50,"meta":{"_tromm":"enter_general","_app":"harmony"},"totalView":88,"recentView":0,"fbCommentCount":0,"useDefaultOpencomment":"true","viewCoverImage":null,"pcCoverImage":"","useLatestOrderComment":"false","cp":null,"viewCoverVideo":null,"summary":[{"title":"","desc":"<p>언제나 매끈한 피부, 번짐 없이 완벽한 메이크업을 유지하는 스타들,&nbsp;<span style=\"color: inherit;\">대체 그 비결이 무엇일까?</span></p> \n<p><span style=\"color: inherit;\"><br></span></p> \n<p><span style=\"color: inherit;\">셀럽들에겐 메이크업이 무너지기 쉬운 마의 오후 3시를 '보송보송'하게 견디는 방법이 있다고 한다.</span></p> \n<p> </p>"},{"title":"","desc":"<div style=\"text-align: center\"> \n <img src=\"https://t1.daumcdn.net/liveboard/emoticon/kakaofriends/v3/mujiandconspecial/emot_015_x3.gif\" alt=\"노려보기\" class=\"sa-emoticon\"> \n</div> \n<div style=\"text-align: center\">\n  그걸 왜 이제 말해? \n</div>"},{"title":"","desc":"<p style=\"text-align: center; \"><u>언제나 처음 화장한 것처럼</u></p> \n<p style=\"text-align: center; \"><br></p> \n<p style=\"text-align: center; \">번짐 없이 매끈한 스타들의</p> \n<p style=\"text-align: center; \">수정 메이크업 비결을 모아봤다.</p> \n<p> </p>"}],"version":6,"title":"연예인 화장이 오래가는 이유","editor":"MpN4oCIF2E","updateTime":1619679013959,"regTime":1619593942147,"titleRaw":"연예인 화장이 오래가는 이유","img":"https://t1.daumcdn.net/liveboard/newsade/cc736899902e4246ad13c40f23d3f094.PNG","path":"newsade/makeupfix","isHiddenComment":"false","isDisabledComment":true,"isPublic":true},{"id":"608a44653c69bd3782375bad","channelKey":"issue","serviceKey":"tourplus","publishKey":"608a44653c69bd3782375bad","consumerId":"1boon","status":"published","description":"","coverImage":"https://t1.daumcdn.net/liveboard/tourplus/2b74fa67622949ca88bfceffb6da9ea3.JPG","serviceTemplate":"listicle","publishTime":1619677806909,"tags":["환급","소비자","2020년","코로나19","항공권"],"filteredTags":null,"bizKeywords":null,"totalShareCount":null,"shareClickCount":null,"socialIncomingCount":0,"meta":{"_tromm":"trip_info","_app":"harmony"},"totalView":14,"recentView":0,"fbCommentCount":0,"useDefaultOpencomment":"true","viewCoverImage":"https://t1.daumcdn.net/liveboard/tourplus/2b74fa67622949ca88bfceffb6da9ea3.JPG","pcCoverImage":"","useLatestOrderComment":"false","cp":null,"viewCoverVideo":null,"summary":[{"title":null,"desc":"<p> </p> \n<div> \n <br> \n</div> \n<div style=\"text-align: center; \"> \n <b>​ </b> \n</div> \n<div style=\"text-align: center; \"> \n <b>사례 1. 입국 금지 조치에도 환급 불가 조건을 이유로 숙박대금 환급 거부 </b> \n</div> \n<div style=\"text-align: center; \"> \n <br> \n</div> \n<div> \n <br> \n</div> \n<div> \n <br> \n</div> \n<div> \n <br> \n</div> \n<div> \n <br> \n</div> \n<div>\n  A씨는 2020년 4월 27일부터 29일까지 2박 3일간 머물 호주 여행을 위해 5개월 전인 2019년 12월말에 140여만원을 들여 호텔 예약을 했다. 그러나 2020년 3월경 코로나19 확산에 따른 호주의 한국인 입국 금지 조치로 여행이 불가해 호텔에 취소 및 환급을 요청했으나 ‘환급 불가 상품’을 예약했다는 이유로 환급을 거부당했다. \n</div> \n<div> \n <br> \n</div> \n<div> \n</div> \n<div> \n</div> \n<div> \n</div> \n<div> \n</div> \n<div> \n</div> \n<div> \n</div> \n<div> \n</div> \n<div> \n</div> \n<div> \n</div> \n<div> \n</div> \n<div> \n</div> \n<div> \n</div> \n<div> \n</div>"},{"title":"","desc":"<p> </p> \n<div style=\"text-align: center; \"> \n <b><br></b> \n</div> \n<div style=\"text-align: center; \"> \n <b>사례 2. 항공편 결항에 따른 환급 요청에도 수수료 공제 </b> \n</div> \n<div style=\"text-align: center; \"> \n <br> \n</div> \n<div> \n <br> \n</div> \n<div> \n <br> \n</div> \n<div> \n <br> \n</div> \n<div> \n <br> \n</div> \n<div>\n  B씨는 2020년 4월 30일부터 5월 9일까지 일정으로 유럽 여행을 계획했다. 이를 위해 2019년 12월 4일 해외 항공사 홈페이지에서 유럽 왕복 항공권을 124만원에 결제했다. 하지만 2020년 4월 14일 항공사로부터 코로나19 확산에 따른 항공편 취소 통보 메일을 받았고 환급을 요청했으나 항공사는 20만원 상당의 금액을 수수료로 공제한다고 안내했다. \n</div> \n<div> \n <br> \n</div> \n<div> \n</div> \n<div> \n</div> \n<div> \n</div> \n<div> \n</div> \n<div> \n</div> \n<div> \n</div> \n<div> \n</div>"},{"title":"","desc":"<p> </p> \n<div> \n <br> \n</div> \n<div style=\"text-align: center; \"> \n <b>사례 3. 해외 항공 예약 대행 사이트의 연락두절 </b> \n</div> \n<div> \n <br> \n</div> \n<div> \n <br> \n</div> \n<div> \n <br> \n</div> \n<div> \n <br> \n</div> \n<div> \n <br> \n</div> \n<div>\n  C씨는 지난 해 3월경 신혼여행을 위해 해외 항공 예약 대행 사이트를 통해 하와이행 항공권 2매를 구매했다. 그러나 코로나19 확산으로 운항 스케줄이 변경돼 취소를 원하면 예약 사이트를 통해 환급 진행할 것을 항공사로부터 안내 받았다. 이에 해외 예약 대행 사이트에 메일, 전화, 채팅 등으로 연락을 취했지만 연락이 되지 않았다. \n</div> \n<div> \n <br> \n</div> \n<div> \n</div> \n<div> \n</div> \n<div> \n</div> \n<div> \n</div> \n<div> \n</div> \n<div> \n</div> \n<div> \n</div>"}],"version":2,"title":"호텔‧항공권 환불 민원 증가세…소비자 유의사항 8가지","editor":"RFNG78gcAx","updateTime":1619677806909,"regTime":1619674213772,"titleRaw":"호텔‧항공권 환불 민원 증가세…소비자 유의사항 8가지","img":"https://t1.daumcdn.net/liveboard/tourplus/2b74fa67622949ca88bfceffb6da9ea3.JPG","path":"tourplus/608a44653c69bd3782375bad","isHiddenComment":"false","isDisabledComment":false,"isPublic":true},{"id":"608a3afa18c79f2de6012dc2","channelKey":"enter","serviceKey":"sbsnoriter","publishKey":"608a3afa18c79f2de6012dc2","consumerId":"1boon","status":"published","description":"","coverImage":"https://t1.daumcdn.net/liveboard/sbsnoriter/091fa533c29543d0a6f52cdcddc3ae7e.JPG","serviceTemplate":"listicle","publishTime":1619677806664,"tags":["맛남의광장","성유리","백종원","음식","요리","레시피","SBS","예능"],"filteredTags":null,"bizKeywords":null,"totalShareCount":null,"shareClickCount":null,"socialIncomingCount":384,"meta":{"_tromm":"enter_general","_app":"harmony","_approvedAt":"1619677883646","_isApproved":"true"},"totalView":545,"recentView":0,"fbCommentCount":0,"useDefaultOpencomment":"true","viewCoverImage":null,"pcCoverImage":"","useLatestOrderComment":"false","cp":null,"viewCoverVideo":null,"summary":[{"title":null,"desc":"<p style=\"text-align: center;\">6년 전 &lt;힐링캠프&gt;에 출연했던 백쌤</p> \n<p style=\"text-align: center;\"><br></p> \n<p style=\"text-align: center;\">당시에는 지금처럼 예능감 뿜뿜할</p> \n<p style=\"text-align: center;\">시절이 아니라서ㅋㅋㅋㅋ</p> \n<p style=\"text-align: center;\">요리에 전념하셨는데요ㅋㅋㅋ</p>"},{"title":"","desc":"<p style=\"text-align: center;\">간밤에 야식을 불러일으켰던</p> \n<p style=\"text-align: center;\"><b>백쌤의 &lt;애호박전&gt;</b></p>"}],"version":15,"title":"성유리를 예능으로 컴백시킨 백종원의 요리","editor":"MgUQAa2EBg","updateTime":1619677806664,"regTime":1619671802501,"titleRaw":"성유리를 예능으로 컴백시킨 백종원의 요리","img":"https://t1.daumcdn.net/liveboard/sbsnoriter/091fa533c29543d0a6f52cdcddc3ae7e.JPG","path":"sbsnoriter/608a3afa18c79f2de6012dc2","isHiddenComment":"false","isDisabledComment":true,"isPublic":true},{"id":"6089785a3c69bd3782375707","channelKey":"trending","serviceKey":"forsnap","publishKey":"6089785a3c69bd3782375707","consumerId":"1boon","status":"published","description":"","coverImage":"https://t1.daumcdn.net/liveboard/forsnap/8532b3f4c16942998d48e8c849130e5f.JPG","serviceTemplate":"listicle","publishTime":1619677806455,"tags":["연예인","다이어트","운동","답사고"],"filteredTags":null,"bizKeywords":null,"totalShareCount":null,"shareClickCount":null,"socialIncomingCount":526,"meta":{"_tromm":"enter_general","_app":"harmony"},"totalView":1043,"recentView":0,"fbCommentCount":0,"useDefaultOpencomment":"true","viewCoverImage":null,"pcCoverImage":"","useLatestOrderComment":"false","cp":null,"viewCoverVideo":null,"summary":[{"title":"옥주현 또 한번 다이어트 명언? \"사실 라면 맛있지 않다\"","desc":"뮤지컬 배우 옥주현이 또 한 번 다이어트 명언을 쏟아냈다. 지난 27일 방송된 tvN '온앤오프'에는 옥주현과 배우 유이가 출연했다. 이날 방송에서는 식단관리를 하며 건강한 몸을 만들고 있는 유이의 일상이 그려졌다. 점심으로 친언니와 닭가슴살을 먹기로 한 유이는 식사에 앞서 먹방을 틀었다. 그런데 하필 유이가 고른 영상이 '치킨 먹방' 영상이었다. 유이는"},{"title":"","desc":"<p>지난 27일 방송된 tvN '온앤오프'에서 옥주현이 또 한 번 다이어트 명언을 쏟아냈습니다. 옥주현은 자신의 경험을 빗대며 \"나도 (라면이 먹고 싶을 때) 라면을 맛을 아니까 그 맛을 상상하면서 내 음식을 먹는다\"라며 \"사실 라면은 먹을 때 맛있지 않다\"고 말했습니다. 하지만 일동이 공감하지 못하자 다시 \"끓일때 냄새가 더 맛있다\"고 정정해 설명했습니다.</p>"},{"title":"연예계 미스터리 '옥주현 괴력'이 만들어지는 과정...ㄷㄷ | tvN 210427 방송","desc":""}],"version":15,"title":"'관리의 신' 옥주현이 전격 공개한 운동과 식단","editor":"iYp7e8V9VF","updateTime":1619677806455,"regTime":1619621978263,"titleRaw":"'관리의 신' 옥주현이 전격 공개한 운동과 식단","img":"https://t1.daumcdn.net/liveboard/forsnap/8532b3f4c16942998d48e8c849130e5f.JPG","path":"forsnap/6089785a3c69bd3782375707","isHiddenComment":"false","isDisabledComment":true,"isPublic":true},{"id":"608a05fc3c69bd3782375850","channelKey":"issue","serviceKey":"14f","publishKey":"608a05fc3c69bd3782375850","consumerId":"1boon","status":"published","description":"","coverImage":"https://t1.daumcdn.net/liveboard/14f/a7a68ee4503d48db9444017007de74b9.png","serviceTemplate":"listicle","publishTime":1619677523880,"tags":["경호원","플렉스","월급클라쓰","14f","일사에프"],"filteredTags":null,"bizKeywords":null,"totalShareCount":null,"shareClickCount":null,"socialIncomingCount":1,"meta":{"_tromm":"society","_app":"harmony"},"totalView":25,"recentView":0,"fbCommentCount":0,"useDefaultOpencomment":"true","viewCoverImage":null,"pcCoverImage":"","useLatestOrderComment":"false","cp":null,"viewCoverVideo":null,"summary":[{"title":"목숨 걸고 VIP 지키면서, 본인 통장은 \uD83D\uDC36털린 31세 경호원.ssul / 14F","desc":"이번주 직장인\n5년차 경호원 ‘장은혜’\n\n“코시국에 일 없어서 0원찍고, 대출 받았는데요..”\n\n-고금리 대출 갈아타기 \"대환대출\"\n-신용점수 올리기\n-보험비 한 번에 쉽게 돌려받는 방법 \n\n모르면 억울한 깨알같은 팁들을 알려드립니다\uD83D\uDCB5\uD83D\uDCB8\uD83E\uDDFE\n\n⭐월급클라쓰⭐와 한잔 하실 분들은\nmbc14fclass@gmail.com 으로 신청서 보내주세요~$$$\n\n#여자경호원 #경호원월급 #현영재테크"},{"title":null,"desc":"<p style=\"text-align: center; \"><b>내 돈 빼고 다 지킨다&nbsp;</b></p> \n<p style=\"text-align: center; \">\uD83D\uDCB8\uD83D\uDE0E✋\uD83C\uDFFB\uD83D\uDD76</p> \n<p style=\"text-align: center; \"><br></p> \n<p style=\"text-align: center; \">목숨걸고 VIP 지키면서 본인의 통장은 탈탈 털린</p> \n<p style=\"text-align: center; \">5년차 경호원&nbsp;</p> \n<p style=\"text-align: center; \"><br></p> \n<p style=\"text-align: center; \"><i>“코시국에 일 없어서 0원찍고, 대출 받았는데요..” </i></p> \n<p style=\"text-align: center; \"><br></p> \n<p style=\"text-align: center; \">-고금리 대출 갈아타기 \"대환대출\" </p> \n<p style=\"text-align: center; \">-신용점수 올리기 </p> \n<p style=\"text-align: center; \">-보험비 한 번에 쉽게 돌려받는 방법 </p> \n<p style=\"text-align: center; \"><br></p> \n<p style=\"text-align: center; \">모르면 억울한 깨알같은 팁들을&nbsp;</p> \n<p style=\"text-align: center; \">유튜브 14F 월급클라쓰에서 알려드립니다\uD83D\uDCB5\uD83D\uDCB8\uD83E\uDDFE</p> \n<p style=\"text-align: center; \"> </p> \n<p style=\"text-align: center; \"> </p> \n<p style=\"text-align: center; \"> </p>"}],"version":7,"title":"본인 잔고빼고 다 지키는 여자 경호원 카드내역털기","editor":"5Af4CJWTui","updateTime":1619677523880,"regTime":1619658235651,"titleRaw":"본인 잔고빼고 다 지키는 여자 경호원 카드내역털기","img":"https://t1.daumcdn.net/liveboard/14f/a7a68ee4503d48db9444017007de74b9.png","path":"14f/608a05fc3c69bd3782375850","isHiddenComment":"false","isDisabledComment":false,"isPublic":true},{"id":"608a4f3d3c69bd3782375c79","channelKey":"enter","serviceKey":"feelthemovie","publishKey":"608a4f3d3c69bd3782375c79","consumerId":"1boon","status":"published","description":"영화 <남자가 사랑할때> 비하인드 & 트리비아 3부","coverImage":"https://t1.daumcdn.net/liveboard/feelthemovie/a5daf8ebb460443599304326322e8b5e.JPG","serviceTemplate":"listicle","publishTime":1619676995118,"tags":["황정민","한혜진","남자가사랑할떄","정만식","강민아","영화뉴스","영화비하인드","필더무비"],"filteredTags":null,"bizKeywords":null,"totalShareCount":null,"shareClickCount":null,"socialIncomingCount":33,"meta":{"_tromm":"movie","_app":"harmony"},"totalView":241,"recentView":0,"fbCommentCount":0,"useDefaultOpencomment":"true","viewCoverImage":null,"pcCoverImage":"","useLatestOrderComment":"false","cp":null,"viewCoverVideo":null,"summary":[{"title":"황정민이 너무 예뻐서 부끄러워 눈도 못 마주쳤다는 여성 배우","desc":"영화 <남자가 사랑할때> 비하인드 & 트리비아 2부"},{"title":"1.영화 조연으로 많이 나오신 이분은 사실 유명한 영화감독","desc":""},{"title":null,"desc":"<p>영화 속 태일(황정민)에게 돈을 빌린 치킨집 사장을 연기한 배우는 황병국으로 영화 &lt;부당거래&gt;, &lt;내부자들&gt;, &lt;돈&gt;, &lt;히트맨&gt;, &lt;이웃사촌&gt; 등 30여 편이 넘는 작품에 출연한 베테랑 연기자다. 영화를 많이 본 관객에게는 매우 익숙한 배우인데 사실 그의 본업은 영화감독이다. &lt;나의 결혼 원정기&gt;, &lt;오프라인&gt;, &lt;특수본&gt;을 연출한 감독인데, 어쩌다 보니 배우일을 더 많이 하게 되었다고 한다.</p>"}],"version":7,"title":"딸에게 실수로 영화속 나쁜 말을 해버린 황정민의 최후","editor":"Kpou0mcYXV","updateTime":1619677621258,"regTime":1619676989588,"titleRaw":"딸에게 실수로 영화속 나쁜 말을 해버린 황정민의 최후","img":"https://t1.daumcdn.net/liveboard/feelthemovie/a5daf8ebb460443599304326322e8b5e.JPG","path":"feelthemovie/608a4f3d3c69bd3782375c79","isHiddenComment":"false","isDisabledComment":false,"isPublic":true},{"id":"608a474e18c79f2de6012ea3","channelKey":"trending","serviceKey":"realfood","publishKey":"shldsnl","consumerId":"1boon","status":"published","description":"“검정콩 ‘청자5호’ 비만 막고 혈당 상승 억제”","coverImage":"https://t1.daumcdn.net/liveboard/realfood/0f11e555c6a84a29afcbe48b42576728.jpg","serviceTemplate":"listicle","publishTime":1619676609823,"tags":["리얼푸드","비만","대사증후군","체중","체지방","혈당"],"filteredTags":null,"bizKeywords":null,"totalShareCount":null,"shareClickCount":null,"socialIncomingCount":877,"meta":{"_tromm":"food","_app":"harmony","_approvedAt":"1619676616040","_isApproved":"true"},"totalView":1128,"recentView":0,"fbCommentCount":0,"useDefaultOpencomment":"true","viewCoverImage":null,"pcCoverImage":"https://t1.daumcdn.net/liveboard/realfood/0f11e555c6a84a29afcbe48b42576728.jpg","useLatestOrderComment":"false","cp":null,"viewCoverVideo":null,"summary":[{"title":null,"desc":"<p>농촌진흥청이 새로 개발한 검정콩, 청자 5호가 비만과 대사증후군 예방에 효과가 있다는 연구 결과가 나왔다. </p> \n<p><br></p> \n<p> </p>"}],"version":2,"title":"우리 검정콩의 체지방 감소 효능","editor":"ClB79dgtaO","updateTime":1619676609823,"regTime":1619674958283,"titleRaw":"우리 검정콩의 체지방 감소 효능","img":"https://t1.daumcdn.net/liveboard/realfood/0f11e555c6a84a29afcbe48b42576728.jpg","path":"realfood/shldsnl","isHiddenComment":"false","isDisabledComment":false,"isPublic":true},{"id":"60826b128dee770a410e5352","channelKey":"trending","serviceKey":"mbcevery1","publishKey":"60826b128dee770a410e5352","consumerId":"1boon","status":"published","description":"","coverImage":"https://t1.daumcdn.net/liveboard/mbcevery1/e79ca4b43155404d85892771203eea14.jpeg","serviceTemplate":"listicle","publishTime":1619676609692,"tags":["달려라댕댕이","김원효","심진화","태풍"],"filteredTags":null,"bizKeywords":null,"totalShareCount":null,"shareClickCount":null,"socialIncomingCount":71,"meta":{"_tromm":"enter_general","_app":"harmony"},"totalView":139,"recentView":0,"fbCommentCount":0,"useDefaultOpencomment":"true","viewCoverImage":null,"pcCoverImage":"https://t1.daumcdn.net/liveboard/mbcevery1/5cfa8e3b2fae4f4fa57ca0c4b585a5e1.jpeg","useLatestOrderComment":"false","cp":null,"viewCoverVideo":null,"summary":[{"title":null,"desc":"<p style=\"text-align: center;\">태풍이의 200일 기념 열게된 파티에서</p> \n<p style=\"text-align: center;\">원효 &amp; 태풍이 진화에게 주는</p> \n<p style=\"text-align: center;\">마지막 선물!</p>"}],"version":2,"title":"그림을 그릴 줄 안다는 한 개그맨 부부의 반려견?","editor":"tkrulrO0xQ","updateTime":1619676609692,"regTime":1619159826229,"titleRaw":"그림을 그릴 줄 안다는 한 개그맨 부부의 반려견?","img":"https://t1.daumcdn.net/liveboard/mbcevery1/e79ca4b43155404d85892771203eea14.jpeg","path":"mbcevery1/60826b128dee770a410e5352","isHiddenComment":"false","isDisabledComment":false,"isPublic":true},{"id":"608a37263c69bd3782375ad7","channelKey":"library","serviceKey":"thescoop","publishKey":"608a37263c69bd3782375ad7","consumerId":"1boon","status":"published","description":"오뚜기의 라면 콜라보","coverImage":"https://t1.daumcdn.net/liveboard/thescoop/fd3e72d6f0af4c8fa08e7247fbed8702.JPG","serviceTemplate":"listicle","publishTime":1619676495642,"tags":["더스쿠프","경제주갅","오뚜기","후추라면","순후추","순후추라면","이마트24","콜라보","토마토케찹","고기리들기름막국수","들기름막국수","풀무원"],"filteredTags":null,"bizKeywords":null,"totalShareCount":null,"shareClickCount":null,"socialIncomingCount":2,"meta":{"_tromm":"economy","_app":"harmony"},"totalView":50,"recentView":0,"fbCommentCount":0,"useDefaultOpencomment":"true","viewCoverImage":null,"pcCoverImage":"https://t1.daumcdn.net/liveboard/thescoop/5286e9ff8d8545389c0c2029730841d4.JPG","useLatestOrderComment":"false","cp":null,"viewCoverVideo":null,"summary":[{"title":null,"desc":"<p style=\"text-align: justify; \"><b>“다 된 라면에 후추 뿌리기.” 오뚜기가 색다른 도전을 시도했다. 3월 출시한 ‘오뚜기 순후추 라면 매운맛’을 통해서다. 이 제품은 1974년 출시한 오뚜기의 대표 제품 ‘순후추’를 라면에 별첨수프로 넣은 게 특징이다. 출시 한달여가 지난 지금 소비자의 반응은 뜨겁다. 순후추뿐만이 아니다. 오뚜기는 ‘토마토케’ ‘들기름’ 등 자사 장수제품을 활용한 콜라보를 연이어 선보이고 있다. 관건은 ‘2위’에 머무는 라면 시장점유율까지 끌어올릴 수 있느냐다.&nbsp;</b></p>"},{"title":"","desc":"<p style=\"text-align: justify;\">토마토케(1971년), 순후추(1974년), 들기름(2009년)…. 한국인의 주방에 하나쯤 있을 법한 이들 제품은 오뚜기의 대표 장수제품이자 시장점유율 1위 제품이다. 요즘 이 제품들이 ‘라면 콜라보’로 등장해 화제를 불러일으키고 있다. <br><br>대표적인 게 토마토케의 패키지를 적용한 ‘스파게티 라면(제품명 스파게티)’이다. 스파게티 라면에 토마토 페이스트가 들어간다는 점에 착안했다. 소비자에게 친숙한 토마토케·패키지 디자인을 스파게티 라면 봉투에 입힌 셈이다. 오뚜기 관계자는 “지난 3월 한정판 패키지로 출시했는데, 소비자 반응이 좋아 바뀐 디자인으로 계속 생산하는 방안을 검토 중이다”고 설명했다.&nbsp;<br><br>4월에는 오뚜기 순후추를 활용한 ‘순후추 라면 매운맛(컵라면)’을 선보였다. 순후추를 별첨 수프로 함께 넣었을 뿐만 아니라, 기존 순후추 패키지 디자인을 라면 용기에 그대로 적용했다.[※참고: 이 제품은 편의점 이마트24와 협업한 상품으로 이마트24에서 판매 중이다.]<span style=\"color: inherit;\"><br></span></p>"},{"title":"","desc":"<p style=\"text-align: justify;\">현재까지 소비자 반응은 뜨겁다. 출시 후 1주일(4월 16~22일) 만에 이마트24 컵라면 판매 순위 3위를 차지했다. 앞서 3월에 출시한 ‘고기리 들기름막국수’도 한달 넘게 화제를 모으고 있다. 온라인 상에서 ‘맛집’으로 유명한 경기도 용인 고기리막국수와 협업해 만들었는데, 오뚜기 들기름을 함께 넣은 게 특징이다.<br><br>배달의민족이나 카카오 앱 등 온라인 채널에서만 판매하고 있음에도 품귀현상이 빚을 정도다. 자사 장수제품을 라면에 접목하는 오뚜기의 ‘콜라보’ 전략이 시장에 통한 셈이다.&nbsp;</p> \n<p style=\"text-align: justify;\"><br></p> \n<p style=\"text-align: justify;\">이은희 인하대(소비자학) 교수는 “브랜드 헤리티지가 있는 순후추, 들기름 등을 활용해 소비자에게 익숙함과 새로움을 동시에 어필하고 있는 것으로 풀이된다”고 설명했다. ‘장수제품+라면’의 효과는 또 있다. 오뚜기가 자사 들기름·순후추 등을 라면에 사용함으로써 시너지 효과를 거둘 수 있다는 점이다. 원가절감과 동시에 매출증가도 기대할 수 있다는 거다.</p>"}],"version":3,"title":"오뚜기, 다 된 라면에 ‘후추’ 뿌렸더니…","editor":"LxRMGNygPF","updateTime":1619676495642,"regTime":1619670822844,"titleRaw":"오뚜기, 다 된 라면에 ‘후추’ 뿌렸더니…","img":"https://t1.daumcdn.net/liveboard/thescoop/fd3e72d6f0af4c8fa08e7247fbed8702.JPG","path":"thescoop/608a37263c69bd3782375ad7","isHiddenComment":"false","isDisabledComment":false,"isPublic":true},{"id":"608a39284d31cb16eb995819","channelKey":"trending","serviceKey":"RHKorea","publishKey":"why","consumerId":"1boon","status":"published","description":"학교와 학원을 가지 않아도 스스로 공부하는 아이로 키우려면 어떻게 해야 할까?","coverImage":"https://t1.daumcdn.net/liveboard/RHKorea/d0700b2cb7a94f0093b720db2f533a6e.JPG","serviceTemplate":"listicle","publishTime":1619676343338,"tags":["하루1질문초등글쓰기의기적","윤희솔","하루3줄초등글쓰기의기적","문해력","초등학생","WHY학습법","자기주도학습","공부"],"filteredTags":null,"bizKeywords":null,"totalShareCount":null,"shareClickCount":null,"socialIncomingCount":6,"meta":{"_app":"harmony","_tromm":"book"},"totalView":65,"recentView":0,"fbCommentCount":0,"useDefaultOpencomment":"true","viewCoverImage":null,"pcCoverImage":"https://t1.daumcdn.net/liveboard/RHKorea/1d08e4818cfb4309a0b8f2c71e4ca3f4.JPG","useLatestOrderComment":"false","cp":null,"viewCoverVideo":null,"summary":[{"title":"","desc":"코로나 19로 인해 학생들이 등교를 못 하는 상황이 오면서 교육계가 '학력 격차'라는 위기를 맞고 있습니다. 학생들이 집에서 온라인 수업을 하게 되면서 중위권이 사라졌다는 것인데요. 학교나 학원 수업에 의지했던 중위권 학생들의 성적이 하위권으로 떨어졌다고 합니다. 이와는 반대로 상위권 학생들은 공부 시간이 확보되어 오히려 성적이 더 좋아졌다고 하네요."},{"title":"","desc":"<p>바로, '혼공' 즉, <b>혼자 공부할 수 있는 능력 여부 때문</b>입니다.</p> \n<p style=\"text-align: justify; \">혼공은 우리가 흔히 알고 있는 <b><u>자기 주도 학습능력</u></b>이에요.</p>"}],"version":8,"title":"공부 실력을 단번에 끌어올리는 자기 주도 학습, '질문'으로 시작하라","editor":"miNfZjrUm7","updateTime":1619676343338,"regTime":1619671336511,"titleRaw":"공부 실력을 단번에 끌어올리는 자기 주도 학습, '질문'으로 시작하라","img":"https://t1.daumcdn.net/liveboard/RHKorea/d0700b2cb7a94f0093b720db2f533a6e.JPG","path":"RHKorea/why","isHiddenComment":"false","isDisabledComment":false,"isPublic":true},{"id":"608a4b5a4d31cb16eb995943","channelKey":"library","serviceKey":"molit","publishKey":"608a4b5a4d31cb16eb995943","consumerId":"1boon","status":"published","description":"","coverImage":"https://t1.daumcdn.net/liveboard/molit/5f1993e4ba6b460297f329c0dd968bfb.jpg","serviceTemplate":"listicle","publishTime":1619676023810,"tags":["국토교통부","국토부","셔클","세종시","콜버스","스마트모빌리티","스마트시티","버스"],"filteredTags":null,"bizKeywords":null,"totalShareCount":null,"shareClickCount":null,"socialIncomingCount":0,"meta":{"_tromm":"real_estate","_app":"harmony"},"totalView":16,"recentView":0,"fbCommentCount":0,"useDefaultOpencomment":"true","viewCoverImage":null,"pcCoverImage":"","useLatestOrderComment":"false","cp":null,"viewCoverVideo":null,"summary":[{"title":null,"desc":"<p>지난 2021년 4월 13일, 세종시 1생활권에서도 셔클이 시범 운행을 시작했습니다. 셔클은 이미 2020년 은평구에서 시험 운행을 시작했는데요. 세종시에서는 올해부터 평일에 12대, 주말에 9대를 배차해 본격적인 운영에 들어갔습니다.</p> \n<p><br></p> \n<p>셔클은 무엇이고, 또 어떻게 이용하면 되는 걸까요? 일주일 동안 직접 타본 생생한 후기와 함께 알려드립니다.</p>"},{"title":"","desc":"<p>셔클은 특정한 지역을 꾸준히 오가는 교통수단인 ‘셔틀’과 모임을 의미하는 ‘서클’을 합친 말입니다. 같은 지역과 커뮤니티에 거주하는 사람들이 편안하고 안전하게 이동할 수 있는 모빌리티라는 의미를 담았죠. </p> \n<p><br></p> \n<p>좀 더 자세히 풀어보자면, 셔클은 마을버스와 콜택시를 합친 모빌리티 서비스입니다. 정해진 노선을 순환하고 무작위의 사람들과 같이 탄다는 점은 버스와 비슷한데요. 반면 어플리케이션을 활용하여 예약한 후 현재 위치에서 가장 가까운 장소에서 기다리고, 차량이 도착하면 탑승하는 건 콜택시와 비슷합니다.</p> \n<p><u> </u></p> \n<p><u> </u></p>"},{"title":"","desc":"<p>셔클은 애플리케이션(이하 앱)으로 이용할 수 있습니다. 앱을 구동하면, GPS를 통해 확인된 내 현재 위치와 행선지를 묻는 칸이 나옵니다. 가고 싶은 곳을 검색하여 확인하면, 몇 명이 탈지 (탑승권인 ‘패스’가 차감됩니다), 또 아동용 카시트가 필요할지 묻는데요. 체크 후 확인을 누르면, 내 위치에서 가장 가까운 탑승지가 표시됩니다.</p>"}],"version":2,"title":"내가 필요할 때 부르면 달려오는 버스?! -남녀노소 누구나 편리하고 안전하게! 세종시 콜","editor":"MthTnDGLbW","updateTime":1619676023810,"regTime":1619675994341,"titleRaw":"내가 필요할 때 부르면 달려오는 버스?! -남녀노소 누구나 편리하고 안전하게! 세종시 콜","img":"https://t1.daumcdn.net/liveboard/molit/5f1993e4ba6b460297f329c0dd968bfb.jpg","path":"molit/608a4b5a4d31cb16eb995943","isHiddenComment":"false","isDisabledComment":false,"isPublic":true},{"id":"608a464518c79f2de6012e85","channelKey":"library","serviceKey":"sfdirect","publishKey":"608a464518c79f2de6012e85","consumerId":"1boon","status":"published","description":"","coverImage":"https://t1.daumcdn.net/liveboard/sfdirect/1223680b2824431cb550c672b63f70ff.jpg","serviceTemplate":"listicle","publishTime":1619676011173,"tags":[],"filteredTags":null,"bizKeywords":null,"totalShareCount":null,"shareClickCount":null,"socialIncomingCount":127,"meta":{"_tromm":"car","_app":"harmony","_approvedAt":"1619676020664","_isApproved":"true"},"totalView":990,"recentView":0,"fbCommentCount":0,"useDefaultOpencomment":"true","viewCoverImage":null,"pcCoverImage":"","useLatestOrderComment":"false","cp":null,"viewCoverVideo":null,"summary":[{"title":null,"desc":"<p><b>평소와 같이 자동차 주행 중! 순간 갑자기 켜진 경고등! </b></p> \n<p>식은땀이 주룩, 계기판 속 경고등만 봐서는 해석이 불가능한 이 순간 당황스러움만 가득해집니다. 경고등의 의미를 몰라 무엇이 문제인지 몰라 불안한 마음으로 주행하신 적 있다면 충분히 공감할 수 있는 상황인데요~! </p> \n<p> </p> \n<p>자동차는 많은 부품이 모여 만들어졌기 때문에 그만큼 경고등의 종류도 다양합니다.</p> \n<p><br></p> \n<p>더군다나 요즘은 자동차의 종류도 다양하기 때문에 자동차 경고등의 종류는 약 60개 이상이라고 합니다. </p> \n<p>이 다양한 자동차 경고등은 어떤 의미가 있고 무슨 문제로 켜졌을지, 함께 알아보겠습니다!</p>"},{"title":"","desc":"<p>자동차 경고등의 약 세 가지 색으로 구분되는데요! </p> \n<p>그 색별로 의미가 다르다고 합니다. </p> \n<p><br></p> \n<p> </p> \n<p><b>빨간색 경고등</b>은 위험 경고 신호로 경고등이 점등되었으나 무리하게 주행 혹은 방치를 할 경우 자동차에 큰 문제가 발생할 수 있어 즉시 점검/확인이 필요한 비상등입니다. </p> \n<p><br></p> \n<p> </p> \n<p><b>노란색 경고등</b>은 주의 신호이며 주행은 가능하지만, 자동차에 이상증세가 감지되어 점검/확인 필요를 알리는 비상등입니다. </p> \n<p><br></p> \n<p> </p> \n<p>이외에 <b>초록색 혹은 파란색</b>으로 뜨는 경고등의 경우 차량의 현재 상태 혹은 수행중인 기능을 알려주는 비상등입니다. </p> \n<p><br></p> \n<p> </p> \n<p>빨간색, 노란색의 경고등은 자동차에 따라서 색상이 다르게 표현될 수 있으며 같은 모양의 경고등이여도 상태에 따라 빨간색 혹은 노란색으로 색상이 다르게 점등될 수 있습니다. </p> \n<p><br></p> \n<p> </p> \n<p>그렇다면 지금 켜져 있는 경고등! 당장 정비를 맡겨야 하는 경고등일까요? </p> \n<p><br></p> \n<p>안전을 위한 표시이기에 의미를 잘 알고 있으면 상황에 맞는 판단을 내릴 수 있습니다. </p> \n<p><br></p> \n<p> </p> \n<p>이제부터 주요 경고등의 의미를 함께 알아볼까요?&nbsp;</p>"}],"version":6,"title":"이 중에서 정확히 아는 경고등은 몇 개? 자동차 계기판 속 경고등 종류와 대처방법!","editor":"KkPAzQBRO4","updateTime":1619676011173,"regTime":1619674693378,"titleRaw":"이 중에서 정확히 아는 경고등은 몇 개?\n자동차 계기판 속 경고등 종류와 대처방법!","img":"https://t1.daumcdn.net/liveboard/sfdirect/1223680b2824431cb550c672b63f70ff.jpg","path":"sfdirect/608a464518c79f2de6012e85","isHiddenComment":"false","isDisabledComment":false,"isPublic":true},{"id":"608a436e18c79f2de6012e56","channelKey":"issue","serviceKey":"tourplus","publishKey":"608a436e18c79f2de6012e56","consumerId":"1boon","status":"published","description":"","coverImage":"https://t1.daumcdn.net/liveboard/tourplus/f5dea0289567465b8cc7c2e6df6ac3c4.png","serviceTemplate":"listicle","publishTime":1619676011001,"tags":["호텔","여행","라스베이거스","가성비","보니"],"filteredTags":null,"bizKeywords":null,"totalShareCount":null,"shareClickCount":null,"socialIncomingCount":7,"meta":{"_tromm":"trip_info","_app":"harmony"},"totalView":46,"recentView":0,"fbCommentCount":0,"useDefaultOpencomment":"true","viewCoverImage":"https://t1.daumcdn.net/liveboard/tourplus/f5dea0289567465b8cc7c2e6df6ac3c4.png","pcCoverImage":"","useLatestOrderComment":"false","cp":null,"viewCoverVideo":null,"summary":[{"title":"","desc":"<p> </p> \n<div style=\"text-align: center; \"> \n <b><br></b> \n</div> \n<div style=\"text-align: center; \"> \n <b>\"더 좋게, 하지만 더 싸게.\" </b> \n</div> \n<div> \n <br> \n</div> \n<div> \n <br> \n</div> \n<div> \n <br> \n</div> \n<div> \n <br> \n</div> \n<div> \n <br> \n</div> \n<div>\n  ​ \n</div> \n<div>\n  가성비를 생각한 여행을 하면 항상 숙소가 가장 고민이다. 숙소에서 상당히 많은 경비를 줄일 수 있는 반면, 너무 질이 떨어지는 숙소에서의 하룻밤은 여행의 피로를 더 쌓을 뿐 풀어주지 않는다. \n</div> \n<div>\n  ​ \n</div> \n<div> \n <br> \n</div> \n<div> \n <br> \n</div> \n<div> \n <br> \n</div> \n<div> \n <br> \n</div> \n<div> \n <br> \n</div> \n<div>\n  유럽, 북미, 남미, 아시아 등 20개국을 여행한 필자가 숙소를 고르는 기준은 딱 3가지다. \n</div> \n<div>\n  ​ \n</div> \n<div> \n <br> \n</div> \n<div> \n <br> \n</div> \n<div> \n <br> \n</div> \n<div> \n <br> \n</div> \n<div style=\"text-align: center;\"> \n <i>1. 위치 </i> \n</div> \n<div style=\"text-align: center;\"> \n <i>숙소가 주요 관광지 혹은 역과 가까운가 </i> \n</div> \n<div style=\"text-align: center;\"> \n <i>2. 청결도 </i> \n</div> \n<div style=\"text-align: center;\"> \n <i>벌레가 나오지 않는 깨끗한 숙소인가 </i> \n</div> \n<div style=\"text-align: center;\"> \n <i>3. 가격 </i> \n</div> \n<div style=\"text-align: center;\"> \n <i>상대적으로 가성비 좋은 숙소인가 </i> \n</div> \n<div style=\"text-align: center;\"> \n <i>이 세 가지를 따져보며 숙소를 예약하면 보통 실패하지 않았다. 하지만 어디서나 예외는 있는 법. 미대륙에서 마주한 최악의 호텔과 최고의 호텔 경험을 공유한다. </i> \n</div> \n<div style=\"text-align: center;\"> \n <i>​ </i> \n</div> \n<div>\n  ​ \n</div> \n<div>\n  ​ \n</div> \n<div> \n <br> \n</div> \n<div>\n  ​ \n</div> \n<div>\n  ​ \n</div> \n<div style=\"text-align: center; \"> \n <b>&nbsp;자본주의 성지, 호텔 천국 라스베이거스 </b> \n</div> \n<div> \n <br> \n</div> \n<div> \n</div> \n<div> \n</div> \n<div> \n</div> \n<div> \n</div> \n<div> \n</div> \n<div> \n</div> \n<div> \n</div> \n<div> \n</div> \n<div> \n</div> \n<div> \n</div> \n<div> \n</div> \n<div> \n</div> \n<div> \n</div> \n<div> \n</div> \n<div> \n</div> \n<div> \n</div> \n<div> \n</div> \n<div> \n</div> \n<div> \n</div> \n<div> \n</div> \n<div> \n</div> \n<div> \n</div> \n<div> \n</div> \n<div> \n</div> \n<div> \n</div> \n<div> \n</div> \n<div> \n</div> \n<div> \n</div> \n<div> \n</div> \n<div> \n</div> \n<div> \n</div> \n<div> \n</div> \n<div> \n</div> \n<div> \n</div> \n<div> \n</div> \n<div> \n</div> \n<div> \n</div>"},{"title":"","desc":"<p> </p> \n<div> \n <br> \n</div> \n<div>\n  라스베이거스는 사실 럭셔리한 호텔의 성지다. 분수쇼로 유명한 벨라지오 호텔부터 화산쇼를 하는 미라지 호텔, 서커스가 펼쳐지는 MGM 호텔, 뉴욕을 축소시켜놓은 뉴욕뉴욕 호텔, 클럽이 유명한 아리아 호텔과 코스모폴리탄 호텔, 로마제국 콘셉트의 시저스 팰리스, 이탈리아 베네치아를 옮겨놓은 듯한 베네시안 호텔까지. 하지만 라스베이거스 여행의 중심지인 '스트립'에 위치한 호텔들은 혼자 여행하는 자들에게 턱없이 높은 가격을 제시한다. \n</div> \n<div>\n  ​ \n</div> \n<div> \n <br> \n</div> \n<div> \n <br> \n</div> \n<div> \n <br> \n</div> \n<div> \n <br> \n</div> \n<div> \n <br> \n</div> \n<div>\n  라스베이거스 스트립을 즐기고는 싶지만 지갑은 가벼웠던 필자는 중심지에서 도보로 10분 떨어진 곳에 숙소를 잡았다. 1박에 약 5만 원 정도 하는 매우 저렴한 호텔이었다. 한국인들의 후기는 거의 찾아볼 수 없었지만 예약사이트의 후기들을 보니 청결하게 유지되는 호텔 같아 보였다. 심지어 스위트룸까지 있으니 믿을 만하다는 생각에 모험을 감행했다. \n</div> \n<div>\n  그렇게 지옥으로의 티켓을 끊게 됐다. \n</div> \n<div>\n  ​ \n</div> \n<div>\n  ​ \n</div> \n<div>\n  ​ \n</div> \n<div>\n  ​ \n</div> \n<div>\n  ​ \n</div> \n<div> \n <br> \n</div> \n<div>\n  ​ \n</div> \n<div style=\"text-align: center; \"> \n <b>호화로운 호텔 가득한 </b> \n</div> \n<div style=\"text-align: center;\"> \n <b>라스베이거스에서 경험한 </b> \n</div> \n<div style=\"text-align: center;\"> \n <b>&nbsp;최악의 호텔 </b> \n</div> \n<div> \n <br> \n</div> \n<div> \n</div> \n<div> \n</div> \n<div> \n</div> \n<div> \n</div> \n<div> \n</div> \n<div> \n</div> \n<div> \n</div> \n<div> \n</div> \n<div> \n</div> \n<div> \n</div> \n<div> \n</div> \n<div> \n</div> \n<div> \n</div> \n<div> \n</div> \n<div> \n</div> \n<div> \n</div> \n<div> \n</div> \n<div> \n</div> \n<div> \n</div> \n<div> \n</div> \n<div> \n</div> \n<div> \n</div> \n<div> \n</div> \n<div> \n</div> \n<div> \n</div> \n<div> \n</div> \n<div> \n</div>"}],"version":2,"title":"가성비 따지는 20개국 여행자가 경험한 최악 VS 최고의 호텔","editor":"RFNG78gcAx","updateTime":1619676011001,"regTime":1619673966845,"titleRaw":"가성비 따지는 20개국 여행자가 경험한 최악 VS 최고의 호텔","img":"https://t1.daumcdn.net/liveboard/tourplus/f5dea0289567465b8cc7c2e6df6ac3c4.png","path":"tourplus/608a436e18c79f2de6012e56","isHiddenComment":"false","isDisabledComment":false,"isPublic":true},{"id":"6087afe23c69bd37823748e2","channelKey":"library","serviceKey":"fortunade","publishKey":"6087afe23c69bd37823748e2","consumerId":"1boon","status":"published","description":"이번 달 당신의 별자리를 더욱 빛내 줄 행운의 컬러를 확인하세요\uD83C\uDF08","coverImage":"https://t1.daumcdn.net/liveboard/fortunade/3e501f86ccab42b9820048353aa71db7.png","serviceTemplate":"swipe","publishTime":1619676010867,"tags":["포춘에이드","월간운세","5월운세","타로운세","무료타로","럭키컬러","별자리운세"],"filteredTags":null,"bizKeywords":null,"totalShareCount":null,"shareClickCount":null,"socialIncomingCount":11,"meta":{"_tromm":"fortune","_app":"harmony"},"totalView":40,"recentView":0,"fbCommentCount":0,"useDefaultOpencomment":"true","viewCoverImage":"https://t1.daumcdn.net/liveboard/fortunade/1440c4cc8a354ff381497212377ccaa7.png","pcCoverImage":"","useLatestOrderComment":"false","cp":null,"viewCoverVideo":null,"summary":[{"title":null,"desc":"<p style=\"text-align: center; \"><br></p> \n<p style=\"text-align: center; \">당신의 별자리 커버를 터치하면\uD83D\uDC46</p> \n<p style=\"text-align: center; \">이번 달 럭키 컬러가\uD83C\uDF08 열립니다.&nbsp;</p>"}],"version":3,"title":"2021년 5월 별자리 럭키 컬러","editor":"z92lYNyYwG","updateTime":1619676010867,"regTime":1619505122444,"titleRaw":"2021년 5월 별자리 럭키 컬러","img":"https://t1.daumcdn.net/liveboard/fortunade/3e501f86ccab42b9820048353aa71db7.png","path":"fortunade/6087afe23c69bd37823748e2","isHiddenComment":"false","isDisabledComment":false,"isPublic":true},{"id":"608a08a43c69bd378237587d","channelKey":"enter","serviceKey":"sbsnoriter","publishKey":"608a08a43c69bd378237587d","consumerId":"1boon","status":"published","description":"","coverImage":"https://t1.daumcdn.net/liveboard/sbsnoriter/b8e82d1c78b24409922b972b0ca01a52.JPG","serviceTemplate":"listicle","publishTime":1619674797230,"tags":["SBS","좋은아침","건강","건강관리","콜라겐","콜라겐흡수","동안"],"filteredTags":null,"bizKeywords":null,"totalShareCount":null,"shareClickCount":null,"socialIncomingCount":344,"meta":{"_tromm":"healthcare","_app":"harmony"},"totalView":799,"recentView":0,"fbCommentCount":0,"useDefaultOpencomment":"true","viewCoverImage":null,"pcCoverImage":"","useLatestOrderComment":"false","cp":null,"viewCoverVideo":null,"summary":[{"title":"","desc":"<p style=\"text-align: center; \">피부 건강과 뼈 건강을 위해 </p> \n<p style=\"text-align: center; \">꼭 챙겨 먹어야 할 콜라겐!&nbsp;</p> \n<p> </p>"},{"title":null,"desc":"<p style=\"text-align: center; \"><span style=\"color: inherit;\">콜라겐이 많이 든 음식! 하면&nbsp;</span><br></p> \n<p style=\"text-align: center; \"><span style=\"color: inherit;\">돼지 껍질이나, 닭발처럼&nbsp;</span></p> \n<p style=\"text-align: center; \"><span style=\"color: inherit;\">쫀쫀하고 쫀득한 음식 많이&nbsp;</span></p> \n<p style=\"text-align: center; \"><span style=\"color: inherit;\">생각하실 텐데요&nbsp;</span></p> \n<p style=\"text-align: center; \"><span style=\"color: inherit;\"><br></span></p> \n<p style=\"text-align: center; \"><span style=\"color: inherit;\">의외로 명태 껍질에</span></p> \n<p style=\"text-align: center; \"><span style=\"color: inherit;\">콜라겐이 듬뿍 들어있다고 해요</span></p>"},{"title":"","desc":"<p style=\"text-align: center;\">특히 명태처럼 어류에든&nbsp;</p> \n<p style=\"text-align: center;\">콜라겐의 경우&nbsp;</p> \n<p style=\"text-align: center;\">30-100개의 아미노산이 결합한&nbsp;</p> \n<p style=\"text-align: center;\">저분자 콜라겐이기 때문에&nbsp;</p> \n<p style=\"text-align: center;\">체내 흡수가 빠르고&nbsp;</p> \n<p style=\"text-align: center;\">피부까지 쉽게 전달된다는 사실!&nbsp;</p>"}],"version":10,"title":"의외로 콜라겐이 듬뿍 들었다는 음식","editor":"ecbWNg4JQA","updateTime":1619674797230,"regTime":1619658916580,"titleRaw":"의외로 콜라겐이 듬뿍 들었다는 음식","img":"https://t1.daumcdn.net/liveboard/sbsnoriter/b8e82d1c78b24409922b972b0ca01a52.JPG","path":"sbsnoriter/608a08a43c69bd378237587d","isHiddenComment":"false","isDisabledComment":false,"isPublic":true},{"id":"608a465418c79f2de6012e88","channelKey":"trending","serviceKey":"realfood","publishKey":"sdhlsdk0h","consumerId":"1boon","status":"published","description":"배더덕 스무디","coverImage":"https://t1.daumcdn.net/liveboard/realfood/fa3de77b7e71448d9ed4b9343b8efffe.JPG","serviceTemplate":"listicle","publishTime":1619674711360,"tags":["리얼푸드","미세먼지","블렌더","바이타믹스","컨테이너","봄"],"filteredTags":null,"bizKeywords":null,"totalShareCount":null,"shareClickCount":null,"socialIncomingCount":257,"meta":{"_tromm":"recipe","_app":"harmony","_approvedAt":"1619674714983","_isApproved":"true"},"totalView":383,"recentView":0,"fbCommentCount":0,"useDefaultOpencomment":"true","viewCoverImage":null,"pcCoverImage":"https://t1.daumcdn.net/liveboard/realfood/fa3de77b7e71448d9ed4b9343b8efffe.JPG","useLatestOrderComment":"false","cp":null,"viewCoverVideo":null,"summary":[{"title":null,"desc":"<p>봄의 불청객하면 ‘미세먼지’가 떠오르죠. 미세 먼지가 몸 속에서 배출되지 못하고 기관지와 폐에 쌓일 경우, 비염과 기관지염, 천식 등을 유발할 수 있습니다. </p> \n<p><br></p> \n<p> </p>"}],"version":2,"title":"기관지에 좋은 더덕. 스무디로 맛있게","editor":"ClB79dgtaO","updateTime":1619674711360,"regTime":1619674708399,"titleRaw":"기관지에 좋은 더덕. 스무디로 맛있게","img":"https://t1.daumcdn.net/liveboard/realfood/fa3de77b7e71448d9ed4b9343b8efffe.JPG","path":"realfood/sdhlsdk0h","isHiddenComment":"false","isDisabledComment":false,"isPublic":true},{"id":"608a33393c69bd3782375ab5","channelKey":"trending","serviceKey":"forsnap","publishKey":"608a33393c69bd3782375ab5","consumerId":"1boon","status":"published","description":"","coverImage":"https://t1.daumcdn.net/liveboard/forsnap/665a6023b1c747d099cdb546af8228dd.JPG","serviceTemplate":"listicle","publishTime":1619674206491,"tags":["연예인","답사고"],"filteredTags":null,"bizKeywords":null,"totalShareCount":null,"shareClickCount":null,"socialIncomingCount":48846,"meta":{"_tromm":"enter_general","_app":"harmony","_approvedAt":"1619675000993","_isApproved":"true"},"totalView":62645,"recentView":0,"fbCommentCount":0,"useDefaultOpencomment":"true","viewCoverImage":null,"pcCoverImage":"","useLatestOrderComment":"false","cp":null,"viewCoverVideo":null,"summary":[{"title":"","desc":"<p>MBC '라디오스타'에서 코미디언 임라라, 손민수 커플이 무명시절부터 현재에 이르기까지의 일화를 털어놓았습니다. 임라라와 손민수는 유튜브 채널 '엔조이커플'을 운영 중이고, 현재 206만 명의 구독자를 보유하고 있습니다.</p>"},{"title":"'엔조이커플' 손민수 \"무명 때 임라라에 '개그맨 1호 이혼' 제안\"","desc":"개그맨 출신 유튜버 손민수가 무명시절 여자친구 임라라에게 '개그맨 1호 이혼 부부'를 제안했었다고 털어놨다. 28일 방송된 MBC '라디오스타'에서는 '엔조이커플' 손민수와 임라라가 출연한 모습이 전파를 탔다. 개그맨 출신으로 오랜 기간 무명을 겪었다는 두 사람은 한 때 수입이 합쳐서 30만원이 되지 않았다고 밝혀 눈길을 끌었다. 또 헌혈하면 영화표를 준"},{"title":"","desc":"<p>무명 시절, 임라라와 손민수의 수입이 30만 원일 때도 있었다고 합니다. 손민수는 \"돈이 너무 없으니까 영화 보는 건 내가 책임지고 싶었다. 헌혈을 하면 티켓을 준데 2주마다 헌혈을 해서 영화 데이트를 했다. 전혈을 하면 2달 1번인데, 혈장 헌혈은 2주마다 할 수 있었다\"고 했습니다.&nbsp;<span style=\"color: inherit;\">그러면서 \"헌혈을 30번 이상 해서 훈장도 받았다\"고 했습니다.&nbsp;</span></p> \n<p> </p>"}],"version":15,"title":"한달에 외제차 한대 값 번다고 밝힌 코미디언 커플","editor":"iYp7e8V9VF","updateTime":1619674206491,"regTime":1619669817665,"titleRaw":"한달에 외제차 한대 값 번다고 밝힌 코미디언 커플","img":"https://t1.daumcdn.net/liveboard/forsnap/665a6023b1c747d099cdb546af8228dd.JPG","path":"forsnap/608a33393c69bd3782375ab5","isHiddenComment":"false","isDisabledComment":true,"isPublic":true},{"id":"608a302218c79f2de6012d1a","channelKey":"enter","serviceKey":"sbsnoriter","publishKey":"608a302218c79f2de6012d1a","consumerId":"1boon","status":"published","description":"","coverImage":"https://t1.daumcdn.net/liveboard/sbsnoriter/cb0c7b5f9ee64e509bfd265348d608b8.JPG","serviceTemplate":"listicle","publishTime":1619674206353,"tags":["트로트","이찬원","김희재","SBS","예능","가수","공감"],"filteredTags":null,"bizKeywords":null,"totalShareCount":null,"shareClickCount":null,"socialIncomingCount":382,"meta":{"_tromm":"enter_general","_app":"harmony","_approvedAt":"1619674212438","_isApproved":"true"},"totalView":546,"recentView":0,"fbCommentCount":0,"useDefaultOpencomment":"true","viewCoverImage":null,"pcCoverImage":"","useLatestOrderComment":"false","cp":null,"viewCoverVideo":null,"summary":[{"title":"[필수시청♥] 김희재×이찬원, 시범공연으로 보여주는 ‘둥지♬’","desc":""},{"title":"","desc":"<p style=\"text-align: center;\">트로트의 대세를 이끌고 있는</p> \n<p style=\"text-align: center;\"><b>김희재x이찬원</b></p> \n<p style=\"text-align: center;\"><br></p> \n<p style=\"text-align: center;\">트로트 아이돌 다운 상큼함으로</p> \n<p style=\"text-align: center;\">청량미 넘치는 화보를 공개했습니다-★</p>"},{"title":null,"desc":"<p style=\"text-align: center;\">최근 트로트에서는 드물게 몽환 섹시 콘셉트로</p> \n<p style=\"text-align: center;\"><b>신곡 '따라 따라와'를 발표한 김희재</b></p> \n<p style=\"text-align: center;\"><br></p> \n<p style=\"text-align: center;\">사실 청량 미 보다 치명 섹시 트로트돌 별명이</p> \n<p style=\"text-align: center;\">매우 마음에 들었다곸ㅋㅋㅋㅋㅋ</p> \n<p style=\"text-align: center;\"><br></p> \n<p style=\"text-align: center;\">젊은 연령층까지 공략하기 위해 많은 노력 중!</p>"}],"version":10,"title":"엄마들 원픽이라는 트롯계 청량돌ㅋㅋ","editor":"MgUQAa2EBg","updateTime":1619674206353,"regTime":1619669026653,"titleRaw":"엄마들 원픽이라는 트롯계 청량돌ㅋㅋ","img":"https://t1.daumcdn.net/liveboard/sbsnoriter/cb0c7b5f9ee64e509bfd265348d608b8.JPG","path":"sbsnoriter/608a302218c79f2de6012d1a","isHiddenComment":"false","isDisabledComment":false,"isPublic":true}],"pagingInfo":{"currentPageIndex":1,"totalPageCount":15521,"totalRecordCount":310401,"pageSize":20,"hasPrev":false,"hasNext":true}}